Workbook
Name aCotizar: Tabla!$B$183:$E$183
Name Avellaneda: Tabla!$B$163:$E$163
Name BoppBlanco: Tabla!$L$36:$L$74
Name BoppCristal: Tabla!$I$36:$I$74
Name BoppMate: Tabla!$J$36:$J$74
Name BoppMetalizado: Tabla!$K$36:$K$74
Name BoppPerladoBlanco: Tabla!$M$36:$M$74
Name Boulogne_Ituzaingo: Tabla!$B$168:$E$168
Name Caba: Tabla!$B$164:$E$164
Name CastCristal: Tabla!$N$36:$N$74
Name CastMetalizado: Tabla!$O$36:$O$74
Name Cliente: Tabla!$C$191:$C$194
Name Dias: Tabla!$A$199:$A$201
Name Escobar: Tabla!$B$179:$E$179
Name EsperaXhr: Tabla!$B$181:$E$181
Name FoilAluminio: Tabla!$P$36:$P$74
Name Garin_Ezeiza: Tabla!$B$176:$E$176
Name JLSuarez: Tabla!$B$171:$E$171
Name KmApartirdelos50km: Tabla!$B$182:$E$182
Name LaPlata: Tabla!$B$165:$E$165
Name Lujan: Tabla!$B$180:$E$180
Name Material: Tabla!$F$15:$F$29
Name Merlo: Tabla!$B$174:$E$174
Name Moron: Tabla!$B$170:$E$170
Name Munro: Tabla!$B$166:$E$166
Name Otro: Tabla!$R$36:$R$74
Name PapelSeda: Tabla!$Q$36:$Q$74
Name Pilar: Tabla!$B$178:$E$178
Name PoliesterCristal: Tabla!$F$36:$F$74
Name PoliesterMetalizado: Tabla!$H$36:$H$74
Name PoliesterSaran: Tabla!$G$36:$G$74
Name PolietilenoBlanco: Tabla!$B$36:$B$74
Name PolietilenoCristal: Tabla!$A$36:$A$74
Name PolietilenoDpk: Tabla!$C$36:$C$74
Name PolietilenoEvohBco: Tabla!$E$36:$E$74
Name PolietilenoEvohCtal: Tabla!$D$36:$D$74
Name Quilmes: Tabla!$B$162:$E$162
Name SanFernando_BellaVista: Tabla!$B$175:$E$175
Name SanJusto_PPodesta: Tabla!$B$172:$E$172
Name SanMartin: Tabla!$B$167:$E$167
Name Tigre: Tabla!$B$173:$E$173
Name Tortuguitas___Moreno: Tabla!$B$177:$E$177
Name Vendedor: Tabla!$A$191:$A$194
Name Zona: Tabla!$B$162:$E$183

Sheet Tabla
A1: OPERATIVOS
A4: Sector | B4: Valor Hora USD | C4: Produccion mts x min | D4: Setup | E4: Scrap
A5: Impresión | B5: =+[1]Produccion!$B$2 -> 58.46 | C5: =+[1]Produccion!$D$2 -> 20000 | D5: =+[1]Produccion!$E$2 -> 1.5 | E5: =+[1]Produccion!$F$2 -> 0
A6: Laminanción | B6: =+[1]Produccion!$B$3 -> 41.35 | C6: =+[1]Produccion!$D$3 -> 16000 | D6: =+[1]Produccion!$E$3 -> 0.5 | E6: =+[1]Produccion!$F$3 -> 0
A7: Rebobinado | B7: =+[1]Produccion!$B$4 -> 39.54 | C7: =+[1]Produccion!$D$4 -> 8000 | D7: =+[1]Produccion!$E$4 -> 0 | E7: =+[1]Produccion!$F$4 -> 0.05
A8: Confección | B8: =+[1]Produccion!$B$5 -> 60.01 | E8: =+[1]Produccion!$F$5 -> 0.15 | F8: =+[1]Produccion!$G$5 -> 100 | G8: =+[1]Produccion!$H$5 -> 0.1 | H8: =+[1]Produccion!$I$5 -> 100
A9: Troquel | F9: =+[1]Produccion!$G$6 -> 100
A10: Picotera | B10: =+[1]Produccion!$B$7 -> 20.003333 | C10: 20 | D10: =+[1]Produccion!$E$7 -> 0.5 | E10: =+[1]Produccion!$F$7 -> 0.05 | F10: =+[1]Produccion!$G$7 -> 100
A12: MATERIAL
A15: Material | B15: Tipo | C15: Peso Esp. | D15: Precio USD | F15: PlastiAndino | T15: Item | U15: Material | V15: Proveedor | W15: Valor | Y15: Condiciones
A16: PolietilenoCristal | B16: Pe Ctal | C16: 0.92 | D16: =+[1]Materiales!$B$2 -> 3.1435674 | F16: Ingepol | U16: Zipper x 11 mm | V16: Flexigrip | W16: 350 | X16: x 1000 mts | Y16: Valor a 30 dias F.F.
A17: PolietilenoBlanco | B17: Pe Bco | C17: 0.92 | D17: =+[1]Materiales!$B$3 -> 3.3235674 | F17: Mateu | U17: Tela Doble Fax | V17: 3M | W17: 505 | X17: x 23 mts
A18: PolietilenoDpk | B18: Pe Ctal DPK | C18: 0.92 | D18: =+[1]Materiales!$B$4 -> 3.3235674 | F18: Polifilm | U18: Pe Ctal Samseng | V18: HQ Film | X18: x Kgrs | Y18: Valor a 30 dias F.F.
A19: PolietilenoEvohCtal | B19: Pe EVOH Ctal | C19: 1 | D19: =+[1]Materiales!$B$5 -> 0 | F19: Plastipren | U19: Pe Ctal Doypack | V19: HQ Film | W19: U$S 2,90 | X19: x Kgrs | Y19: Valor a 30 dias F.F.
A20: PolietilenoEvohBco | B20: Pe EVOH Bco | C20: 1 | D20: =+[1]Materiales!$B$6 -> 8 | F20: Silvapack | U20: Pe Bco Doypack | V20: HQ Film | W20: U$S 3,20 | X20: x Kgrs | Y20: Valor a 30 dias F.F.
A21: PoliesterCristal | B21: Pet Ctal | C21: 1.41 | D21: =+[1]Materiales!$B$9 -> 3.65 | F21: Enimar | U21: Pe Ctal Pastas | V21: HQ Film | X21: x Kgrs | Y21: Valor a 30 dias F.F.
A22: PoliesterSaran | B22: Pet Saran | C22: 1.41 | D22: =+[1]Materiales!$B$10 -> 5.85 | F22: Osda | U22: Pet Ctal 12 mic | V22: Enimar | W22: U$S 4.50 | X22: x Kgrs | Y22: Valor a 30 dias F.F.
A23: PoliesterMetalizado | B23: Pet Met | C23: 1.41 | D23: =+[1]Materiales!$B$12 -> 4.85 | F23: Dalfilm | U23: Pet Ctal Saran 14 mic | V23: Enimar | W23: U$S 7.40 | X23: x Kgrs | Y23: Valor a 30 dias F.F.
A24: BoppCristal | B24: Bopp Ctal | C24: 0.91 | D24: =+[1]Materiales!$B$15 -> 3.75 | F24: Alufilm | U24: Bopp ctal 20 a 35 mic | V24: Enimar | W24: U$S 3.50 | X24: x Kgrs | Y24: Valor a 30 dias F.F.
A25: BoppMate | B25: Bopp Mat | C25: 0.91 | D25: =+[1]Materiales!$B$16 -> 4 | F25: Vitopel | U25: Bopp Met 20 a 35 mic | V25: Enimar | W25: U$S 4.45 | X25: x Kgrs | Y25: Valor a 30 dias F.F.
A26: BoppMetalizado | B26: Bopp Met | C26: 0.91 | D26: =+[1]Materiales!$B$17 -> 4.55 | F26: Copyfilm | U26: Pet Ctal 12 mic | V26: Dalfilm | W26: U$S 3.80 | X26: x Kgrs | Y26: Contado
A27: BoppBlanco | B27: Bopp Bco | C27: 0.95 | D27: =+[1]Materiales!$B$18 -> 4 | F27: Silvapack
A28: BoppPerladoBlanco | B28: Bopp Per Bco | C28: 1.1 | D28: =+[1]Materiales!$B$19 -> 4 | F28: Tratitran | U28: Bopp ctal | V28: Dalfilm | W28: U$S 3.70 | X28: x Kgrs | Y28: Menos de 5 Tn
A29: CastCristal | B29: Cast Ctal | C29: 0.91 | D29: =+[1]Materiales!$B$20 -> 3.4 | F29: Otro | U29: Bopp Met/Perla/Mate | V29: Dalfilm | W29: U$S 4.50 | X29: x Kgrs | Y29: Menos de 5 Tn
A30: CastMetalizado | B30: Cast Met | C30: 0.91 | D30: =+[1]Materiales!$B$21 -> 0
A31: FoilAluminio | B31: Foil Al | C31: 2.7 | D31: =+[1]Materiales!$B$24 -> 8.8253033 | U31: Bopp ctal | V31: Dalfilm | W31: U$S 3.60 | X31: x Kgrs | Y31: Mas de 5 Tn
A32: PapelSeda | B32: Papel SD | C32: 1.1 | D32: =+[1]Materiales!$B$25 -> 0 | U32: Bopp Met/Perla/Mate | V32: Dalfilm | W32: U$S 4.40 | X32: x Kgrs | Y32: Mas de 5 Tn
A33: Otro | B33: Otro | C33: 0 | D33: 0
U34: Bopp Bco 20 mic | V34: Dalfilm | W34: U$S 4.75 | X34: x Kgrs | Y34: Contado | Z34: El material demora 60 dias
A35: PolietilenoCristal | B35: PolietilenoBlanco | C35: PolietilenoDpk | D35: PolietilenoEvohCtal | E35: PolietilenoEvohBco | F35: PoliesterCristal | G35: PoliesterSaran | H35: PoliesterMetalizado | I35: BoppCristal | J35: BoppMate | K35: BoppMetalizado | L35: BoppBlanco | M35: BoppPerladoBlanco | N35: CastCristal | O35: CastMetalizado | P35: FoilAluminio | Q35: PapelSeda | R35: Otro
A36: 30 | B36: 30 | C36: 30 | D36: 30 | E36: 30 | F36: 12 | G36: 14 | H36: 12 | I36: 17 | J36: 17 | K36: 17 | L36: 19 | M36: 20 | N36: 17 | O36: 17 | P36: 8 | Q36: 0 | R36: 0
A37: 35 | B37: 35 | C37: 35 | D37: 35 | E37: 35 | I37: 20 | J37: 20 | K37: 20 | M37: 25 | N37: 20 | O37: 20 | P37: 10
A38: 40 | B38: 40 | C38: 40 | D38: 40 | E38: 40 | I38: 25 | K38: 25 | M38: 30 | N38: 25 | O38: 25 | P38: 15
A39: 45 | B39: 45 | C39: 45 | D39: 45 | E39: 45 | I39: 30 | K39: 30 | N39: 30 | O39: 30
A40: 50 | B40: 50 | C40: 50 | D40: 50 | E40: 50 | I40: 35 | K40: 35 | N40: 35 | O40: 35
A41: 55 | B41: 55 | C41: 55 | D41: 55 | E41: 55
A42: 60 | B42: 60 | C42: 60 | D42: 60 | E42: 60
A43: 65 | B43: 65 | C43: 65 | D43: 65 | E43: 65
A44: 70 | B44: 70 | C44: 70 | D44: 70 | E44: 70
A45: 75 | B45: 75 | C45: 75 | D45: 75 | E45: 75
A46: 80 | B46: 80 | C46: 80 | D46: 80 | E46: 80
A47: 85 | B47: 85 | C47: 85 | D47: 85 | E47: 85
A48: 90 | B48: 90 | C48: 90 | D48: 90 | E48: 90
A49: 95 | B49: 95 | C49: 95 | D49: 95 | E49: 95
A50: 100 | B50: 100 | C50: 100 | D50: 100 | E50: 100
A51: 105 | B51: 105 | C51: 105 | D51: 105 | E51: 105
A52: 110 | B52: 110 | C52: 110 | D52: 110 | E52: 110
... A74: 220 | B74: 220 | C74: 220 | D74: 220 | E74: 220
A76: IMPRESIÓN
A79: Tela Doble Fax | B79: =+[1]Tela!$C$3 -> 399 | F79: SI | G79: NO
A81: TINTA PET / BOPP
A82: PRECIO TINTAS
A83: FLINT
B85: GAMA EXPANDIDA
A86: COLORES | B86: V | C86: N | D86: G | E86: B | F86: C | G86: M | H86: Y | I86: K | J86: TOTAL | L86: =+[1]Produccion!$A$12 -> Mangas | N86: Cono
A87: PRECIO | B87: =+[1]Tintas!$C$15 -> 18.462 | C87: =+[1]Tintas!$C$14 -> 7.164 | D87: =+[1]Tintas!$C$16 -> 8.256 | E87: =+[1]Tintas!$C$20 -> 5.445 | F87: =+[1]Tintas!$C$10 -> 7.3 | G87: =+[1]Tintas!$C$11 -> 7.035 | H87: =+[1]Tintas!$C$9 -> 6.7 | I87: =+[1]Tintas!$C$12 -> 6.07 | J87: =AVERAGE(B87:I87) -> 8.304 | L87: =+[1]Produccion!$A$13 -> 35 | N87: =+[1]Produccion!$C$13 -> 3 | O87: =+[1]Produccion!$D$13 -> 0.043
A88: % | B88: 0.11 | C88: 0.11 | D88: 0.19 | E88: 1 | F88: 0.23 | G88: 0.29 | H88: 0.15 | I88: 0.11 | L88: =+[1]Produccion!$A$14 -> 36 | N88: =+[1]Produccion!$C$14 -> 6 | O88: =+[1]Produccion!$D$14 -> 0.052
A89: COSTO | B89: =+B87*B88 -> 2.03082 | C89: =+C87*C88 -> 0.78804 | D89: =+D87*D88 -> 1.56864 | E89: =+E87*E88 -> 5.445 | F89: =+F87*F88 -> 1.679 | G89: =+G87*G88 -> 2.04015 | H89: =+H87*H88 -> 1.005 | I89: =+I87*I88 -> 0.6677 | J89: =SUM(B89:I89) -> 15.22435 | L89: =+[1]Produccion!$A$15 -> 38
A90: BARNIZ | B90: =+[1]Tintas!$C$3 -> 5.39 | L90: =+[1]Produccion!$A$16 -> 40
A91: % | F91: 0.3 | G91: 0.25 | I91: 0.3 | L91: =+[1]Produccion!$A$17 -> 42
A92: COSTO | B92: =+$B90*B91 -> 0 | C92: =+$B90*C91 -> 0 | D92: =+$B90*D91 -> 0 | E92: =+$B90*E91 -> 0 | F92: =+$B90*F91 -> 1.617 | G92: =+$B90*G91 -> 1.3475 | H92: =+$B90*H91 -> 0 | I92: =+$B90*I91 -> 1.617 | J92: =SUM(B92:I92) -> 4.5815 | L92: =+[1]Produccion!$A$18 -> 44
A93: DY ALARGUE | B93: =+[1]Diluyente!$C$3 -> 1.86 | L93: =+[1]Produccion!$A$19 -> 45
B94: 0.2 | C94: 0.2 | D94: 0.2 | E94: 0.2 | F94: 0.2 | G94: 0.2 | H94: 0.2 | I94: 0.2 | L94: =+[1]Produccion!$A$20 -> 47
B95: =+$B93*B94 -> 0.372 | C95: =+$B93*C94 -> 0.372 | D95: =+$B93*D94 -> 0.372 | E95: =+$B93*E94 -> 0.372 | F95: =+$B93*F94 -> 0.372 | G95: =+$B93*G94 -> 0.372 | H95: =+$B93*H94 -> 0.372 | I95: =+$B93*I94 -> 0.372 | J95: =SUM(B95:I95) -> 2.976 | L95: =+[1]Produccion!$A$21 -> 48
A96: COSTO TINTAS | B96: =(B89*(100%-(B91+B94)))+B92+B95 -> 1.996656 | C96: =(C89*(100%-(C91+C94)))+C92+C95 -> 1.002432 | D96: =(D89*(100%-(D91+D94)))+D92+D95 -> 1.626912 | E96: =(E89*(100%-(E91+E94)))+E92+E95 -> 4.728 | F96: =(F89*(100%-(F91+F94)))+F92+F95 -> 2.8285 | G96: =(G89*(100%-(G91+G94)))+G92+G95 -> 2.8415825 | H96: =(H89*(100%-(H91+H94)))+H92+H95 -> 1.176 | I96: =(I89*(100%-(I91+I94)))+I92+I95 -> 2.32285 | J96: =SUM(B96:I96) -> 18.522932 | L96: =+[1]Produccion!$A$22 -> 50
B97: =+B96*4/1000 -> 0.007986624 | C97: =+C96*4/1000 -> 0.004009728 | D97: =+D96*4/1000 -> 0.006507648 | E97: =+E96*4/1000 -> 0.018912 | F97: =+F96*4/1000 -> 0.011314 | G97: =+G96*4/1000 -> 0.01136633 | H97: =+H96*4/1000 -> 0.004704 | I97: =+I96*4/1000 -> 0.0092914 | J97: =AVERAGE(B97:I97) -> 0.0092614662 | L97: =+[1]Produccion!$A$23 -> 52
L98: =+[1]Produccion!$A$24 -> 54
A99: DY LIMPIEZA | B99: =+[1]Diluyente!$C$18 -> 1.25 | L99: =+[1]Produccion!$A$25 -> 56
A100: DY RECUP | B100: =0.9*2 -> 1.8 | L100: =+[1]Produccion!$A$26 -> 58
B101: =+[1]Diluyente!$C$5 -> 2.09 | L101: =+[1]Produccion!$A$27 -> 60
A102: =20/2 -> 10 | B102: =+B101*$A102 -> 20.9 | L102: =+[1]Produccion!$A$28 -> 64
L103: =+[1]Produccion!$A$29 -> 66
L104: =+[1]Produccion!$A$30 -> 70
A105: PET | C105: MARDI | F105: PROCESO | L105: =+[1]Produccion!$A$31 -> 74
A106: COLORES | B106: 318 | C106: 485 | D106: 308 | E106: B | F106: C | G106: M | H106: Y | I106: K | J106: TOTAL | L106: =+[1]Produccion!$A$32 -> 80
A107: PRECIO | B107: =+(+D87*6%)+(F87*6%) -> 0.93336 | C107: =+(+G87*50%)+(H87*50%) -> 6.8675 | D107: =+(+F87*94%)+(I87*6%) -> 7.2262 | E107: =+E87 -> 5.445 | F107: =+[1]Tintas!$C$6 -> 7.3 | G107: =+[1]Tintas!$C$7 -> 7.035 | H107: =+[1]Tintas!$C$5 -> 6.7 | I107: =+[1]Tintas!$C$8 -> 6.07 | J107: =AVERAGE(B107:I107) -> 5.9471325
A108: % | B108: 0.636 | C108: 0.171 | D108: 0.301 | E108: 0.9685 | F108: 0.151 | G108: 0.261 | H108: 0.654 | I108: 0.283
A109: COSTO | B109: =+B107*B108 -> 0.59361696 | C109: =+C107*C108 -> 1.1743425 | D109: =+D107*D108 -> 2.1750862 | E109: =+E107*E108 -> 5.2734825 | F109: =+F107*F108 -> 1.1023 | G109: =+G107*G108 -> 1.836135 | H109: =+H107*H108 -> 4.3818 | I109: =+I107*I108 -> 1.71781 | J109: =SUM(B109:I109) -> 18.254573
A110: BARNIZ | B110: =+[1]Tintas!$C$3 -> 5.39
A111: % | B111: 0.88 | C111: 0 | D111: 0 | E111: 0 | F111: 0 | G111: 0 | H111: 0 | I111: 0
A112: COSTO | B112: =+$B110*B111 -> 4.7432 | C112: =+$B110*C111 -> 0 | D112: =+$B110*D111 -> 0 | E112: =+$B110*E111 -> 0 | F112: =+$B110*F111 -> 0 | G112: =+$B110*G111 -> 0 | H112: =+$B110*H111 -> 0 | I112: =+$B110*I111 -> 0 | J112: =SUM(B112:I112) -> 4.7432
A113: DY ALARGUE | B113: =+B93 -> 1.86
B114: 0.2 | C114: 0.2 | D114: 0.2 | E114: 0.2 | F114: 0.2 | G114: 0.2 | H114: 0.2 | I114: 0.2
B115: =+$B113*B114 -> 0.372 | C115: =+$B113*C114 -> 0.372 | D115: =+$B113*D114 -> 0.372 | E115: =+$B113*E114 -> 0.372 | F115: =+$B113*F114 -> 0.372 | G115: =+$B113*G114 -> 0.372 | H115: =+$B113*H114 -> 0.372 | I115: =+$B113*I114 -> 0.372 | J115: =SUM(B115:I115) -> 2.976
A116: COSTO TINTAS | B116: =(B109*(100%-B114-B111)+(B115*B108)) -> 0.18910264 | C116: =(C109*(100%-C114-C111)+(C115*C108)) -> 1.003086 | D116: =(D109*(100%-D114-D111)+(D115*D108)) -> 1.852041 | E116: =(E109*(100%-E114-E111)+(E115*E108)) -> 4.579068 | F116: =(F109*(100%-F114-F111)+(F115*F108)) -> 0.938012 | G116: =(G109*(100%-G114-G111)+(G115*G108)) -> 1.566 | H116: =(H109*(100%-H114-H111)+(H115*H108)) -> 3.748728 | I116: =(I109*(100%-I114-I111)+(I115*I108)) -> 1.479524 | J116: =SUM(B116:I116) -> 15.355562
A119: LAMINACIÓN
F121: SI | G121: NO | H121: BI
A122: SOLVENTE LESS | B122: =+[1]Adhesivos!$D$3 -> 2
A123: Compuesto | B123: =+[1]Adhesivos!$C$4 -> 9.9 | C123: =+[1]Adhesivos!$D$4 -> 0.63
A124: Catalizador | B124: =+[1]Adhesivos!$C$5 -> 9.9 | C124: =+[1]Adhesivos!$D$5 -> 0.37
A126: SOLVENTE | B126: =+[1]Adhesivos!$D$10 -> 4
A127: Compuesto | B127: =+[1]Adhesivos!$E$15 -> 11.13
A130: VARIOS
A132: Zipper | B132: =+'[1]Zipper y Picos'!$D$3 -> 0.04290429 | D132: Troquel | E132: =+'[1]Zipper y Picos'!$D$9 -> 0.015
A133: Caja | B133: =+[1]Caja!$D$3 -> 0.37644224 | D133: Pico | E133: =+'[1]Zipper y Picos'!$D$6/1000 -> 0.032231716
A134: CONFECCION
C136: Pouche | E136: Doypack | G136: Pouch c/Zipper | I136: Doypack c/Zipper | K136: 4Costuras
A137: Ancho envases | C137: Golpes por min. | D137: Envases por hora | E137: Golpes por min. | F137: Envases por hora | G137: Golpes EXTRA x min. | H137: Envases por hora | I137: Golpes EXTRA x min. | J137: Envases por hora | K137: Golpes por min. | L137: Envases por hora
A139: 100 | B139: mm | C139: =+[1]Produccion!$C$38 -> 75 | D139: =C139*60 -> 4500 | E139: =+[1]Produccion!$E$38 -> 70 | F139: =E139*60 -> 4200 | G139: =+[1]Produccion!$G$38 -> 5 | H139: =(G139*60)+D139 -> 4800 | I139: =+[1]Produccion!$I$38 -> 5 | J139: =(I139*60)+F139 -> 4500 | K139: =+[1]Produccion!$K$38 -> 25 | L139: =K139*60 -> 1500
A140: 120 | B140: mm | C140: =+[1]Produccion!$C$39 -> 75 | D140: =C140*60 -> 4500 | E140: =+[1]Produccion!$E$39 -> 70 | F140: =E140*60 -> 4200 | G140: =+[1]Produccion!$G$39 -> 5 | H140: =(G140*60)+D140 -> 4800 | I140: =+[1]Produccion!$I$39 -> 5 | J140: =(I140*60)+F140 -> 4500 | K140: =+[1]Produccion!$K$38 -> 25 | L140: =K140*60 -> 1500
...

Sheet Bobina
A1: 4PACK | C1: Cliente | K1: A | L1: Ajuste | N1: 0 | Q1: Vendedor | S1: AK
A2: BOBINA | C2: Bobina / Flow | K2: Nro. de Cotizacion: | M2: 001908 | O2: / 2025 | Q2: =TODAY() -> 46286 | R2: Ajuste | S2: 0
B3: Ancho | D3: 44 | F3: cm | G3: Modulos Ancho | J3: 2 | K3: cm | L3: Paso | N3: 25 | O3: cm | P3: Modulos Desarrollo | R3: 2 | S3: cm
A4: Proveedor | B4: Vitopel | D4: BoppCristal | F4: 20 | G4: mic | P4: =+N3*R3 -> 50 | Q4: Desarrollo | R4: =IF(P4=Tabla!$L$87,Tabla!$L$87,IF(P4=Tabla!$L$88,Tabla!$L$88,IF(P4=Tabla!$L$89,Tabla!$L$89,IF(P4=Tabla!$L$90,Tabla!$L$90,IF(P4=Tabla!$L$91,Tabla!$L$91,IF(P4=Tabla!$L$92,Tabla!$L$92,IF(P4=Tabla!$L$93,Tabla!$L$93,IF(P4=Tabla!$L$94,Tabla!$L$94,IF(P4=Tabla!$L$95,Tabla!$L$95,IF(P4=Tabla!$L$96,Tabla!$L$96,IF(P4=Tabla!$L$97,Tabla!$L$97,IF(P4=Tabla!$L$98,Tabla!$L$98,IF(P4=Tabla!$L$99,Tabla!$L$99,IF(P4=Tabla!$L$100,Tabla!$L$100,IF(P4=Tabla!$L$101,Tabla!$L$101,IF(P4=Tabla!$L$102,Tabla!$L$102,IF(P4=Tabla!$L$103,Tabla!$L$103,IF(P4=Tabla!$L$104,Tabla!$L$104,IF(P4=Tabla!$L$105,Tabla!$L$105,"NO DISPBLE"))))))))))))))))))) -> 50 | S4: cm
B5: Ingepol | D5: BoppCristal | F5: 20 | G5: mic | H5: Cantidad | J5: 67000 | K5: mts | L5: Peso Neto | N5: NO | O5: 6 | P5: Mangas Disponibles | R5: 35 | S5: cm
B6: Otro | D6: Otro | F6: 0 | G6: mic | H6: Peso | J6: =(SUM(L15:L17))*(J5/1000) -> 2146.144 | K6: Kgrs | L6: x Bobina | N6: 25 | O6: kg | P6: Diseños | R6: 1 | S6: Blanco %
B7: IMPRESIÓN | D7: SI | E7: RePRINT | F7: NO | G7: LAM SIN SOLVENTE | J7: SI | L7: CON SOLVENTE | N7: NO | P7: Cambios | R7: 0 | S7: 100
B8: Ancho Refilado | D8: SI | E8: =+D3*J3 -> 88 | F8: cm | G8: Impresión Scrap | J8: 0 | K8: cm | L8: U$S | N8: =((IF(B15=Tabla!A16,Tabla!C16,IF(B15=Tabla!$A$16,Tabla!$C$16,IF(B15=Tabla!$A$17,Tabla!$C$17,IF(B15=Tabla!$A$18,Tabla!$C$18,IF(B15=Tabla!$A$19,Tabla!$C$19,IF(B15=Tabla!$A$20,Tabla!$C$20,IF(B15=Tabla!$A$21,Tabla!$C$21,IF(B15=Tabla!$A$22,Tabla!$C$22,IF(B15=Tabla!$A$23,Tabla!$C$23,IF(B15=Tabla!$A$24,Tabla!$C$24,IF(B15=Tabla!$A$25,Tabla!$C$25,IF(B15=Tabla!$A$26,Tabla!$C$26,IF(B15=Tabla!$A$27,Tabla!$C$27,IF(B15=Tabla!$A$28,Tabla!$C$28,IF(B15=Tabla!$A$29,Tabla!$C$29,IF(B15=Tabla!$A$30,Tabla!$C$30,IF(B15=Tabla!$A$31,Tabla!$C$31,IF(B15=Tabla!$A$32,Tabla!$C$32,IF(B15=Tabla!$A$33,Tabla!$C$33,””))))))))))))))))))))*(H15/1000)*(J8/100)*E15)*F15 -> 0 | P8: Colores | R8: 8 | S8: =+R8*(R6+R7) -> 8
B9: Ancho Lamina | D9: =+E8+2 -> 90 | F9: cm | G9: Laminación Scrap | J9: 0 | K9: cm | L9: U$S | N9: =((IF(B16=Tabla!A17,Tabla!C17,IF(B16=Tabla!$A$16,Tabla!$C$16,IF(B16=Tabla!$A$17,Tabla!$C$17,IF(B16=Tabla!$A$18,Tabla!$C$18,IF(B16=Tabla!$A$19,Tabla!$C$19,IF(B16=Tabla!$A$20,Tabla!$C$20,IF(B16=Tabla!$A$21,Tabla!$C$21,IF(B16=Tabla!$A$22,Tabla!$C$22,IF(B16=Tabla!$A$23,Tabla!$C$23,IF(B16=Tabla!$A$24,Tabla!$C$24,IF(B16=Tabla!$A$25,Tabla!$C$25,IF(B16=Tabla!$A$26,Tabla!$C$26,IF(B16=Tabla!$A$27,Tabla!$C$27,IF(B16=Tabla!$A$28,Tabla!$C$28,IF(B16=Tabla!$A$29,Tabla!$C$29,IF(B16=Tabla!$A$30,Tabla!$C$30,IF(B16=Tabla!$A$31,Tabla!$C$31,IF(B16=Tabla!$A$32,Tabla!$C$32,IF(B16=Tabla!$A$33,Tabla!$C$33,””))))))))))))))))))))*(H16/1000)*(J9/100)*E16)*F16 -> 0 | P9: % Impreso | R9: 100
G10: Bilaminación Scrap | J10: 0 | K10: cm | L10: U$S | N10: =((IF(B17=Tabla!A18,Tabla!C18,IF(B17=Tabla!$A$16,Tabla!$C$16,IF(B17=Tabla!$A$17,Tabla!$C$17,IF(B17=Tabla!$A$18,Tabla!$C$18,IF(B17=Tabla!$A$19,Tabla!$C$19,IF(B17=Tabla!$A$20,Tabla!$C$20,IF(B17=Tabla!$A$21,Tabla!$C$21,IF(B17=Tabla!$A$22,Tabla!$C$22,IF(B17=Tabla!$A$23,Tabla!$C$23,IF(B17=Tabla!$A$24,Tabla!$C$24,IF(B17=Tabla!$A$25,Tabla!$C$25,IF(B17=Tabla!$A$26,Tabla!$C$26,IF(B17=Tabla!$A$27,Tabla!$C$27,IF(B17=Tabla!$A$28,Tabla!$C$28,IF(B17=Tabla!$A$29,Tabla!$C$29,IF(B17=Tabla!$A$30,Tabla!$C$30,IF(B17=Tabla!$A$31,Tabla!$C$31,IF(B17=Tabla!$A$32,Tabla!$C$32,IF(B17=Tabla!$A$33,Tabla!$C$33,””))))))))))))))))))))*(H17/1000)*(J10/100)*E17)*F17 -> 0 | P10: Flete | Q10: 1 | R10: Caba | S10: 3500
G11: Valor por Kgrs al contado | P11: U$S | Q11: =+P36 -> 7.351486
G12: Valor por Kgrs a | K12: 30 | L12: días FF | N12: =INDEX(Tabla!$B$199:$B$201,MATCH(K12,Tabla!$A$199:$A$201,0))/100 -> 0.041666667 | P12: U$S | Q12: =+P38 -> 7.6577979
B14: Detalle | E14: Mic | F14: Valor x Kgrs (U$S) | H14: Mtrs a trabajar | J14: Kgrs a trabajar | K14: Kgrs x 1000 Mts | L14: Kgrs x 1000 Mts | M14: Valor x 1000 mts | O14: Valor Kgrs | Q14: Incidencia
A15: 1 | B15: =+D4 -> BoppCristal | E15: =+F4 -> 20 | F15: =(IF(B15=Tabla!$A$16,Tabla!$D$16,IF(B15=Tabla!$A$17,Tabla!$D$17,IF(B15=Tabla!$A$18,Tabla!$D$18,IF(B15=Tabla!$A$19,Tabla!$D$19,IF(B15=Tabla!$A$20,Tabla!$D$20,IF(B15=Tabla!$A$21,Tabla!$D$21,IF(B15=Tabla!$A$22,Tabla!$D$22,IF(B15=Tabla!$A$23,Tabla!$D$23,IF(B15=Tabla!$A$24,Tabla!$D$24,IF(B15=Tabla!$A$25,Tabla!$D$25,IF(B15=Tabla!$A$26,Tabla!$D$26,IF(B15=Tabla!$A$27,Tabla!$D$27,IF(B15=Tabla!$A$28,Tabla!$D$28,IF(B15=Tabla!$A$29,Tabla!$D$29,IF(B15=Tabla!$A$30,Tabla!$D$30,IF(B15=Tabla!$A$31,Tabla!$D$31,IF(B15=Tabla!$A$32,Tabla!$D$32,IF(B15=Tabla!$A$33,Tabla!$D$33)))))))))))))))))))*A15 -> 3.75 | H15: =+J5+(1500*(R6+R7)) -> 68500 | J15: =(IF(B15=Tabla!$A$16,Tabla!$C$16,IF(B15=Tabla!$A$17,Tabla!$C$17,IF(B15=Tabla!$A$18,Tabla!$C$18,IF(B15=Tabla!$A$19,Tabla!$C$19,IF(B15=Tabla!$A$20,Tabla!$C$20,IF(B15=Tabla!$A$21,Tabla!$C$21,IF(B15=Tabla!$A$22,Tabla!$C$22,IF(B15=Tabla!$A$23,Tabla!$C$23,IF(B15=Tabla!$A$24,Tabla!$C$24,IF(B15=Tabla!$A$25,Tabla!$C$25,IF(B15=Tabla!$A$26,Tabla!$C$26,IF(B15=Tabla!$A$27,Tabla!$C$27,IF(B15=Tabla!$A$28,Tabla!$C$28,IF(B15=Tabla!$A$29,Tabla!$C$29,IF(B15=Tabla!$A$30,Tabla!$C$30,IF(B15=Tabla!$A$31,Tabla!$C$31,IF(B15=Tabla!$A$32,Tabla!$C$32,IF(B15=Tabla!$A$33,Tabla!$C$33,””)))))))))))))))))))*(H15/1000)*((D9+J8)/100)*E15 -> 1122.03 | K15: =(IF(B15=Tabla!$A$16,Tabla!$C$16,IF(B15=Tabla!$A$17,Tabla!$C$17,IF(B15=Tabla!$A$18,Tabla!$C$18,IF(B15=Tabla!$A$19,Tabla!$C$19,IF(B15=Tabla!$A$20,Tabla!$C$20,IF(B15=Tabla!$A$21,Tabla!$C$21,IF(B15=Tabla!$A$22,Tabla!$C$22,IF(B15=Tabla!$A$23,Tabla!$C$23,IF(B15=Tabla!$A$24,Tabla!$C$24,IF(B15=Tabla!$A$25,Tabla!$C$25,IF(B15=Tabla!$A$26,Tabla!$C$26,IF(B15=Tabla!$A$27,Tabla!$C$27,IF(B15=Tabla!$A$28,Tabla!$C$28,IF(B15=Tabla!$A$29,Tabla!$C$29,IF(B15=Tabla!$A$30,Tabla!$C$30,IF(B15=Tabla!$A$31,Tabla!$C$31,IF(B15=Tabla!$A$32,Tabla!$C$32,IF(B15=Tabla!$A$33,Tabla!$C$33,””)))))))))))))))))))*E15*((D9+J8)/100) -> 16.38 | L15: =(IF(B15=Tabla!$A$16,Tabla!$C$16,IF(B15=Tabla!$A$17,Tabla!$C$17,IF(B15=Tabla!$A$18,Tabla!$C$18,IF(B15=Tabla!$A$19,Tabla!$C$19,IF(B15=Tabla!$A$20,Tabla!$C$20,IF(B15=Tabla!$A$21,Tabla!$C$21,IF(B15=Tabla!$A$22,Tabla!$C$22,IF(B15=Tabla!$A$23,Tabla!$C$23,IF(B15=Tabla!$A$24,Tabla!$C$24,IF(B15=Tabla!$A$25,Tabla!$C$25,IF(B15=Tabla!$A$26,Tabla!$C$26,IF(B15=Tabla!$A$27,Tabla!$C$27,IF(B15=Tabla!$A$28,Tabla!$C$28,IF(B15=Tabla!$A$29,Tabla!$C$29,IF(B15=Tabla!$A$30,Tabla!$C$30,IF(B15=Tabla!$A$31,Tabla!$C$31,IF(B15=Tabla!$A$32,Tabla!$C$32,IF(B15=Tabla!$A$33,Tabla!$C$33,””)))))))))))))))))))*E15*(E8/100) -> 16.016 | M15: U$S | N15: =((J15*F15)/(J5/1000))*A15 -> 62.800187 | O15: U$S | P15: =N15/(SUM(L15:L17)) -> 1.9605453 | Q15: =(P15*100)/(P36-P30-P32) -> 33.128812 | R15: %
A16: 1 | B16: =+D5 -> BoppCristal | E16: =+F5 -> 20 | F16: =(IF(B16=Tabla!$A$16,Tabla!$D$16,IF(B16=Tabla!$A$17,Tabla!$D$17,IF(B16=Tabla!$A$18,Tabla!$D$18,IF(B16=Tabla!$A$19,Tabla!$D$19,IF(B16=Tabla!$A$20,Tabla!$D$20,IF(B16=Tabla!$A$21,Tabla!$D$21,IF(B16=Tabla!$A$22,Tabla!$D$22,IF(B16=Tabla!$A$23,Tabla!$D$23,IF(B16=Tabla!$A$24,Tabla!$D$24,IF(B16=Tabla!$A$25,Tabla!$D$25,IF(B16=Tabla!$A$26,Tabla!$D$26,IF(B16=Tabla!$A$27,Tabla!$D$27,IF(B16=Tabla!$A$28,Tabla!$D$28,IF(B16=Tabla!$A$29,Tabla!$D$29,IF(B16=Tabla!$A$30,Tabla!$D$30,IF(B16=Tabla!$A$31,Tabla!$D$31,IF(B16=Tabla!$A$32,Tabla!$D$32,IF(B16=Tabla!$A$33,Tabla!$D$33)))))))))))))))))))*A16 -> 3.75 | H16: =+J5+100 -> 67100 | J16: =(IF(B16=Tabla!$A$16,Tabla!$C$16,IF(B16=Tabla!$A$17,Tabla!$C$17,IF(B16=Tabla!$A$18,Tabla!$C$18,IF(B16=Tabla!$A$19,Tabla!$C$19,IF(B16=Tabla!$A$20,Tabla!$C$20,IF(B16=Tabla!$A$21,Tabla!$C$21,IF(B16=Tabla!$A$22,Tabla!$C$22,IF(B16=Tabla!$A$23,Tabla!$C$23,IF(B16=Tabla!$A$24,Tabla!$C$24,IF(B16=Tabla!$A$25,Tabla!$C$25,IF(B16=Tabla!$A$26,Tabla!$C$26,IF(B16=Tabla!$A$27,Tabla!$C$27,IF(B16=Tabla!$A$28,Tabla!$C$28,IF(B16=Tabla!$A$29,Tabla!$C$29,IF(B16=Tabla!$A$30,Tabla!$C$30,IF(B16=Tabla!$A$31,Tabla!$C$31,IF(B16=Tabla!$A$32,Tabla!$C$32,IF(B16=Tabla!$A$33,Tabla!$C$33,””)))))))))))))))))))*(H16/1000)*((D9+J9)/100)*E16 -> 1099.098 | K16: =(IF(B16=Tabla!$A$16,Tabla!$C$16,IF(B16=Tabla!$A$17,Tabla!$C$17,IF(B16=Tabla!$A$18,Tabla!$C$18,IF(B16=Tabla!$A$19,Tabla!$C$19,IF(B16=Tabla!$A$20,Tabla!$C$20,IF(B16=Tabla!$A$21,Tabla!$C$21,IF(B16=Tabla!$A$22,Tabla!$C$22,IF(B16=Tabla!$A$23,Tabla!$C$23,IF(B16=Tabla!$A$24,Tabla!$C$24,IF(B16=Tabla!$A$25,Tabla!$C$25,IF(B16=Tabla!$A$26,Tabla!$C$26,IF(B16=Tabla!$A$27,Tabla!$C$27,IF(B16=Tabla!$A$28,Tabla!$C$28,IF(B16=Tabla!$A$29,Tabla!$C$29,IF(B16=Tabla!$A$30,Tabla!$C$30,IF(B16=Tabla!$A$31,Tabla!$C$31,IF(B16=Tabla!$A$32,Tabla!$C$32,IF(B16=Tabla!$A$33,Tabla!$C$33,””)))))))))))))))))))*E16*((D9+J8)/100) -> 16.38 | L16: =(IF(B16=Tabla!$A$16,Tabla!$C$16,IF(B16=Tabla!$A$17,Tabla!$C$17,IF(B16=Tabla!$A$18,Tabla!$C$18,IF(B16=Tabla!$A$19,Tabla!$C$19,IF(B16=Tabla!$A$20,Tabla!$C$20,IF(B16=Tabla!$A$21,Tabla!$C$21,IF(B16=Tabla!$A$22,Tabla!$C$22,IF(B16=Tabla!$A$23,Tabla!$C$23,IF(B16=Tabla!$A$24,Tabla!$C$24,IF(B16=Tabla!$A$25,Tabla!$C$25,IF(B16=Tabla!$A$26,Tabla!$C$26,IF(B16=Tabla!$A$27,Tabla!$C$27,IF(B16=Tabla!$A$28,Tabla!$C$28,IF(B16=Tabla!$A$29,Tabla!$C$29,IF(B16=Tabla!$A$30,Tabla!$C$30,IF(B16=Tabla!$A$31,Tabla!$C$31,IF(B16=Tabla!$A$32,Tabla!$C$32,IF(B16=Tabla!$A$33,Tabla!$C$33,””)))))))))))))))))))*E16*(E8/100) -> 16.016 | M16: U$S | N16: =((J16*F16)/(J5/1000))*A16 -> 61.516679 | O16: U$S | P16: =N16/(SUM(L15:L17)) -> 1.9204757 | Q16: =(P16*100)/(P36-P30-P32) -> 32.451727 | R16: %
A17: 1 | B17: =+D6 -> Otro | E17: =+F6 -> 0 | F17: =(IF(B17=Tabla!$A$16,Tabla!$D$16,IF(B17=Tabla!$A$17,Tabla!$D$17,IF(B17=Tabla!$A$18,Tabla!$D$18,IF(B17=Tabla!$A$19,Tabla!$D$19,IF(B17=Tabla!$A$20,Tabla!$D$20,IF(B17=Tabla!$A$21,Tabla!$D$21,IF(B17=Tabla!$A$22,Tabla!$D$22,IF(B17=Tabla!$A$23,Tabla!$D$23,IF(B17=Tabla!$A$24,Tabla!$D$24,IF(B17=Tabla!$A$25,Tabla!$D$25,IF(B17=Tabla!$A$26,Tabla!$D$26,IF(B17=Tabla!$A$27,Tabla!$D$27,IF(B17=Tabla!$A$28,Tabla!$D$28,IF(B17=Tabla!$A$29,Tabla!$D$29,IF(B17=Tabla!$A$30,Tabla!$D$30,IF(B17=Tabla!$A$31,Tabla!$D$31,IF(B17=Tabla!$A$32,Tabla!$D$32,IF(B17=Tabla!$A$33,Tabla!$D$33)))))))))))))))))))*A17 -> 0 | H17: =+J5+100 -> 67100 | J17: =(IF(B17=Tabla!$A$16,Tabla!$C$16,IF(B17=Tabla!$A$17,Tabla!$C$17,IF(B17=Tabla!$A$18,Tabla!$C$18,IF(B17=Tabla!$A$19,Tabla!$C$19,IF(B17=Tabla!$A$20,Tabla!$C$20,IF(B17=Tabla!$A$21,Tabla!$C$21,IF(B17=Tabla!$A$22,Tabla!$C$22,IF(B17=Tabla!$A$23,Tabla!$C$23,IF(B17=Tabla!$A$24,Tabla!$C$24,IF(B17=Tabla!$A$25,Tabla!$C$25,IF(B17=Tabla!$A$26,Tabla!$C$26,IF(B17=Tabla!$A$27,Tabla!$C$27,IF(B17=Tabla!$A$28,Tabla!$C$28,IF(B17=Tabla!$A$29,Tabla!$C$29,IF(B17=Tabla!$A$30,Tabla!$C$30,IF(B17=Tabla!$A$31,Tabla!$C$31,IF(B17=Tabla!$A$32,Tabla!$C$32,IF(B17=Tabla!$A$33,Tabla!$C$33,””)))))))))))))))))))*(H17/1000)*((D9+J10)/100)*E17 -> 0 | K17: =(IF(B17=Tabla!$A$16,Tabla!$C$16,IF(B17=Tabla!$A$17,Tabla!$C$17,IF(B17=Tabla!$A$18,Tabla!$C$18,IF(B17=Tabla!$A$19,Tabla!$C$19,IF(B17=Tabla!$A$20,Tabla!$C$20,IF(B17=Tabla!$A$21,Tabla!$C$21,IF(B17=Tabla!$A$22,Tabla!$C$22,IF(B17=Tabla!$A$23,Tabla!$C$23,IF(B17=Tabla!$A$24,Tabla!$C$24,IF(B17=Tabla!$A$25,Tabla!$C$25,IF(B17=Tabla!$A$26,Tabla!$C$26,IF(B17=Tabla!$A$27,Tabla!$C$27,IF(B17=Tabla!$A$28,Tabla!$C$28,IF(B17=Tabla!$A$29,Tabla!$C$29,IF(B17=Tabla!$A$30,Tabla!$C$30,IF(B17=Tabla!$A$31,Tabla!$C$31,IF(B17=Tabla!$A$32,Tabla!$C$32,IF(B17=Tabla!$A$33,Tabla!$C$33,””)))))))))))))))))))*E17*((D9+J8)/100) -> 0 | L17: =(IF(B17=Tabla!$A$16,Tabla!$C$16,IF(B17=Tabla!$A$17,Tabla!$C$17,IF(B17=Tabla!$A$18,Tabla!$C$18,IF(B17=Tabla!$A$19,Tabla!$C$19,IF(B17=Tabla!$A$20,Tabla!$C$20,IF(B17=Tabla!$A$21,Tabla!$C$21,IF(B17=Tabla!$A$22,Tabla!$C$22,IF(B17=Tabla!$A$23,Tabla!$C$23,IF(B17=Tabla!$A$24,Tabla!$C$24,IF(B17=Tabla!$A$25,Tabla!$C$25,IF(B17=Tabla!$A$26,Tabla!$C$26,IF(B17=Tabla!$A$27,Tabla!$C$27,IF(B17=Tabla!$A$28,Tabla!$C$28,IF(B17=Tabla!$A$29,Tabla!$C$29,IF(B17=Tabla!$A$30,Tabla!$C$30,IF(B17=Tabla!$A$31,Tabla!$C$31,IF(B17=Tabla!$A$32,Tabla!$C$32,IF(B17=Tabla!$A$33,Tabla!$C$33,””)))))))))))))))))))*E17*(E8/100) -> 0 | M17: U$S | N17: =((J17*F17)/(J5/1000))*A17 -> 0 | O17: U$S | P17: =N17/(SUM(L15:L17)) -> 0 | Q17: =(P17*100)/(P36-P30-P32) -> 0 | R17: %
A18: =IF(D7="SI",1,0) -> 1 | B18: Costo Impresora | E18: Prep | F18: Prod | J18: Valor Hs
A19: =IF(F7="SI",1,0) -> 0 | B19: Reprint | E19: =(Tabla!$D$5*R6+1*R7)*A18 -> 1.5 | F19: =(+J5/20000)*A18 -> 3.35 | G19: =(Tabla!$D$5/3)*A19 -> 0 | H19: =(J5/20000)*A19 -> 0 | J19: U$S | K19: =+Tabla!$B$5 -> 58.46 | M19: U$S | N19: =((E19+F19)*K19)/(J5/1000)*A18 -> 4.231806 | O19: U$S | P19: =N19/(SUM(L15:L17)) -> 0.13211182 | Q19: =(P19*100)/(P36-P30-P32) -> 2.2323931 | R19: %
A20: =IF(D7="SI",1,0) -> 1 | B20: Tela Doble Fax | I20: =(+L20/S8)*A19 -> 0 | J20: x Color U$S | L20: =(IF(B20=Tabla!$A$79,((Tabla!$B$79/2300/46)*(D9+J8)*P4),1)*0.75) -> 12.728025 | O20: U$S | P20: =((L20*S8)/J6)*A20 -> 0.047445184 | Q20: =(P20*100)/(P36-P30-P32) -> 0.80171705 | R20: %
A21: =IF(D7="SI",1,0) -> 1 | B21: Tintas + Diluyentes | I21: =(((Tabla!$B$90*0.8)+(Tabla!$B$93*0.2))/1000*2)*A19 -> 0 | J21: Valor grs/mts2 | L21: =(((((Tabla!$J$116-Tabla!$E$116)/1000*2)+((Tabla!$E$116/1000*2)*S7)/100)*R9)/100) -> 0.030711123 | M21: U$S | N21: =(L21*((D9+J8)*10)*A21)*(R8/8) -> 27.640011 | O21: U$S | P21: =N21/(SUM(L15:L17)) -> 0.86288745 | Q21: =(P21*100)/(P36-P30-P32) -> 14.58086 | R21: %
A22: =IF(D7="SI",1,0) -> 1 | B22: Limpieza Diluyentes | E22: =IF(J5>240000,120,IF(J5>210000,96,IF(J5>180000,72,IF(J5>150000,64,IF(J5>120000,48,IF(J5>60000,24,IF(J5>30000,16,12))))))) -> 24 | J22: Valor Lts | L22: =+Tabla!$B$99 -> 1.25 | M22: U$S | N22: =(+L22*E22/J5*1000)*A22 -> 0.44776119 | O22: U$S | P22: =N22/(SUM(L15:L17)) -> 0.013978559 | Q22: =(P22*100)/(P36-P30-P32) -> 0.23620625 | R22: %
A23: =IF(J7="SI",1,IF(J7="BI",2,0)) -> 1 | B23: Costo Laminado | E23: =+Tabla!$D$6*(A23+A25) -> 0.5 | F23: =+J5/Tabla!$C$6*(A24+A25) -> 4.1875 | J23: U$S | K23: =+Tabla!$B$6 -> 41.35 | M23: U$S | N23: =((E23+F23)*K23)/(J5/1000) -> 2.8929571 | O23: U$S | P23: =N23/(SUM(L15:L17)) -> 0.090314594 | Q23: =(P23*100)/(P36-P30-P32) -> 1.5261138 | R23: %
A24: =IF(J7="SI",1,IF(J7="BI",2,0)) -> 1 | B24: Solvent Less | J24: Valor grs/mts2 | L24: =+(Tabla!$B$123/1000*0.55)+(Tabla!$B$124/1000*0.45)*2*A24 -> 0.014355 | M24: U$S | N24: =L24*((D9+J9+J10)*10) -> 12.9195 | O24: U$S | P24: =(N24/(SUM(L15:L17))*A24) -> 0.40333104 | Q24: =(P24*100)/(P36-P30-P32) -> 6.8153888 | R24: %
A25: =IF(N7="SI",1,IF(N7="BI",2,0)) -> 0 | B25: Solvent | J25: Valor grs/mts2 | L25: =+(Tabla!$B$127/1000)*2*A25 -> 0 | M25: U$S | N25: =L25*(D9*10) -> 0 | O25: U$S | P25: =N25/(SUM(L15:L17)) -> 0 | Q25: =(P25*100)/(P36-P30-P32) -> 0 | R25: %
A26: =IF(D8="SI",1,0) -> 1 | B26: Refilado | E26: =+Tabla!$D$7 -> 0 | F26: =+J5/Tabla!$C$7 -> 8.375 | J26: U$S | K26: =+Tabla!$B$7 -> 39.54 | M26: U$S | N26: =((E26+F26)*K26)/(J5/1000) -> 4.9425 | O26: U$S | P26: =(N26/(SUM(L15:L18)))*A26 -> 0.15429883 | Q26: =(P26*100)/(P36-P30-P32) -> 2.6073036 | R26: %
A27: =+Tabla!$E$7 -> 0.05 | B27: % Material Scrap | O27: U$S | P27: =((SUM(P15:P26))*A27) -> 0.27926943 | Q27: =(P27*100)/(P36-P30-P32) -> 4.7190261 | R27: %
A28: =+Q10 -> 1 | B28: Flete | D28: =+R10 -> Caba | E28: =+S10 -> 3500 | F28: =INDEX(Tabla!$B$162:$E$187,MATCH(R10,Tabla!$A$162:$A$187,0),MATCH(S10,Tabla!$B$161:$E$161,0))*A28 -> 114.36436 | O28: U$S | P28: =F28/J6 -> 0.053288296 | Q28: =(P28*100)/(P36-P30-P32) -> 0.90045252 | R28: %
A29: =IF(AND(B15="PolietilenoCristal",B16="Otro"),Tabla!$B$207,IF(AND(B15="PolietilenoBlanco",B16="Otro"),Tabla!$B$207,IF(AND(B15="PolietilenoDpk",B16="Otro"),Tabla!$B$207,IF(AND(B15="PolietilenoEvohCristal",B16="Otro"),Tabla!$B$207,IF(AND(B15="PolietilenoEvohBBo",B16="Otro"),Tabla!$B$207,IF(AND(B15="PoliesterCristal",B16="PolietilenoCristal"),Tabla!$B$210,IF(AND(B15="PoliesterCristal",B16="PolietilenoBlanco"),Tabla!$B$210,IF(AND(B15="PoliesterCristal",B16="PolietilenoDpk"),Tabla!$B$210,IF(AND(B15="PoliesterCristal",B16="PolietilenoEvohCristal"),Tabla!$B$210,IF(AND(B15="PoliesterCristal",B16="PolietilenoEvohBBo"),Tabla!$B$210,IF(AND(B15="PoliesterSaran",B16="PolietilenoCristal"),Tabla!$B$210,IF(AND(B15="PoliesterSaran",B16="PolietilenoBlanco"),Tabla!$B$210,IF(AND(B15="PoliesterSaran",B16="PolietilenoDpk"),Tabla!$B$210,IF(AND(B15="PoliesterSaran",B16="PolietilenoEvohCristal"),Tabla!$B$210,IF(AND(B15="Poliestersaran",B16="PolietilenoEvohBBo"),Tabla!$B$210,IF(AND(B15="BoppCristal",B16="PolietilenoCristal"),Tabla!$B$209,IF(AND(B15="BoppCristal",B16="PolietilenoBlanco"),Tabla!$B$209,IF(AND(B15="BoppBlanco",B16="PolietilenoCristal"),Tabla!$B$209,IF(AND(B15="BoppBlanco",B16="PolietilenoBlanco"),Tabla!$B$209,IF(AND(B15="BoppMate",B16="PolietilenoCristal"),Tabla!$B$209,IF(AND(B15="BoppMate",B16="PolietilenoBlanco"),Tabla!$B$209,IF(AND(B15="BoppPerladoBlanco",B16="PolietilenoCristal"),Tabla!$B$209,IF(AND(B15="BoppPerladoBlanco",B16="PolietilenoBlanco"),Tabla!$B$209,IF(AND(B15="BoppCristal",B16="BoppCristal"),Tabla!$B$208,IF(AND(B15="BoppCristal",B16="BoppBlanco"),Tabla!$B$208,IF(AND(B15="BoppCristal",B16="BoppMate"),Tabla!$B$208,IF(AND(B15="BoppCristal",B16="BoppMetalizado"),Tabla!$B$208,IF(AND(B15="BoppCristal",B16="BoppPerladoBlanco"),Tabla!$B$208,IF(AND(B15="BoppCristal",B16="Otro"),Tabla!$B$208,IF(AND(B15="BoppMate",B16="BoppMetalizado"),Tabla!$B$208,IF(AND(B15="BoppMate",B16="BoppPerladoBlanco"),Tabla!$B$208,IF(AND(B15="BoppCristal",B16="BoppCristal"),Tabla!$B$208,IF(AND(B15="BoppCristal",B16="BoppBlanco"),Tabla!$B$208,IF(AND(B15="BastCristal",B16="BoppMate"),Tabla!$B$208,IF(AND(B15="BoppCristal",B16="BoppMetalizado"),Tabla!$B$208,IF(AND(B15="BoppCristal",B16="BoppPerladoBlanco"),Tabla!$B$208,IF(AND(B15="PoliesterCristal",B16="FoilAluminio"),Tabla!$B$212,IF(AND(B15="PapelSeda",B16="Otro"),Tabla!$B$211,IF(AND(B15="PoliesterCristal",B16="PoliesterMetalizado",B17="PolietilenoCristal"),Tabla!$B$210+5,"ERROR"))))))))))))))))))))))))))))))))))))))) -> 17.5 | B29: Rentabilidad | K29: Financiado | L29: Costo Bruto | O29: U$S | P29: =SUM(P15:P28) -> 5.9179462 | Q29: Financiación Bancaria
A30: =IF(J6<Tabla!$C$206,Tabla!$B$213+Bobina!$A$29,IF(J6<Tabla!$D$206,Tabla!$C$213+Bobina!$A$29,IF(J6<Tabla!$E$206,Tabla!$D$213+Bobina!$A$29,Tabla!$E$213+Bobina!$A$29))) -> 17.5 | B30: % Plus | C30: Cliente | E30: =+K1 -> A | F30: U$S | G30: =+P30*J6 -> 2761.0358 | I30: =+G30/J6 -> 1.2865101 | J30: xKg | K30: =+(P30+P31-R30)-I32 -> 2.1196785 | O30: U$S | P30: =(P34*(A30/100)) -> 1.2865101 | Q30: U$S | R30: =Q12-Q11 -> 0.30631192
A31: =IF(K1="A",Tabla!$E$207,IF(K1="B",Tabla!$F$207,IF(K1="C",Tabla!$G$207,0))) -> 0 | B31: % | C31: Ajuste | E31: =+N1 -> 0 | F31: U$S | G31: =(+P31*J6)+G30 -> 5522.0717 | I31: =+G31/J6 -> 2.5730201 | J31: xKg | K31: =+G31-K32 -> 972.93643 | O31: U$S | P31: =+P36-P29-P32 -> 1.2865101
A32: =IF(S1="AK",Tabla!$B$191,IF(S1="PM",Tabla!$B$192,IF(S1="4P",Tabla!$B$193,Tabla!$B$194)))+S2 -> 2 | B32: % Comision | E32: =+S1 -> AK | F32: U$S | G32: =+I32*J6 -> 315.54695 | I32: =+P32 -> 0.14702972 | J32: xKg | K32: =K30*J6 -> 4549.1352 | O32: U$S | P32: =+P36*(A32/100) -> 0.14702972
A33: 0 | B33: Polímeros | E33: 1 | F33: U$S | G33: =+(D9*(P4+3)*S8*0.055) -> 2098.8 | I33: =+G33/J6 -> 0.97793997 | J33: xKg | O33: U$S | P33: =+I33*A33 -> 0
B34: Rentabilidad Bonificando Polímeros | F34: U$S | G34: =+I34*J6 -> 5522.0717 | I34: =I31-(I33*E33*A33) -> 2.5730201 | J34: xKg | O34: U$S | P34: =+P29/(1-((A30+A32)/100)) -> 7.351486 | Q34: U$S | R34: =+R29/(1-((A30+A32)/100)) -> 0
O35: U$S | P35: =+P34*(E31/100) -> 0 | Q35: U$S | R35: =+R34*(E31/100) -> 0
F36: Valor por Kgrs al contado | O36: U$S | P36: =+P34+P35 -> 7.351486 | Q36: =SUM(Q19,Q23,Q26)+SUM(A29:A32)+E31 -> 43.365811 | R36: %
F37: Valor por Kgrs a | J37: =+K12 -> 30 | K37: días FF | M37: =+N12 -> 0.041666667 | O37: U$S | P37: =P36*N12 -> 0.30631192
O38: U$S | P38: =+P36+P37 -> 7.6577979

Sheet Confeccion DPK
A1: 4PACK | C1: Cliente | K1: A | L1: Ajuste | N1: 9.833 | Q1: Vendedor | S1: AK
A2: DOYPACK | C2: Doypack | K2: Nro. de Cotizacion: | O2: / 2025 | Q2: =TODAY() -> 46286 | S2: Ajuste | T2: 0
B3: Ancho | D3: 11 | F3: cm | G3: Alto | J3: 17 | K3: cm | L3: Fuelle Total | N3: 7 | O3: cm | Q3: ZIPPER | S3: SI
A4: Proveedor | B4: Vitopel | D4: PoliesterCristal | F4: 12 | G4: mic | H4: Envases | J4: 3000 | K4: unidades | R4: TROQUEL | S4: SI
B5: Ingepol | D5: PolietilenoDpk | F5: 90 | G5: mic | H5: Cantidad | J5: =+J4*D3/100 -> 330 | K5: mts | R5: PICO | S5: SI
B6: Otro | D6: Otro | F6: 0 | G6: mic | H6: Peso | J6: =(SUM(L16:L18))*(J5/1000) -> 13.492116 | K6: Kgrs | P6: Modulos en el Ancho | R6: 1 | S6: Calle Interna entre Modulos
B7: IMPRESIÓN | D7: SI | E7: RePRINT | F7: SI | G7: LAMINACION SIN SOLVENTE | J7: SI | K7: CON SOLVENTE | N7: SI | O7: =+N8*R7 -> 44 | P7: Modulos Desarrollo | R7: 4 | S7: 0
B8: Ancho | D8: =(+J3*2)+N3 -> 41 | F8: cm | G8: Impresión Scrap | J8: 0 | K8: cm | L8: Paso | N8: =+D3 -> 11 | O8: cm | P8: Diseños | R8: 1 | S8: Blanco %
B9: Ancho Refilado | D9: =(+D8*R6)+S7 -> 41 | F9: cm | G9: Laminación Scrap | J9: 0 | K9: cm | L9: Desarrollo | N9: =IF(O7=Tabla!$L$87,Tabla!$L$87,IF(O7=Tabla!$L$88,Tabla!$L$88,IF(O7=Tabla!$L$89,Tabla!$L$89,IF(O7=Tabla!$L$90,Tabla!$L$90,IF(O7=Tabla!$L$91,Tabla!$L$91,IF(O7=Tabla!$L$92,Tabla!$L$92,IF(O7=Tabla!$L$93,Tabla!$L$93,IF(O7=Tabla!$L$94,Tabla!$L$94,IF(O7=Tabla!$L$95,Tabla!$L$95,IF(O7=Tabla!$L$96,Tabla!$L$96,IF(O7=Tabla!$L$97,Tabla!$L$97,IF(O7=Tabla!$L$98,Tabla!$L$98,IF(O7=Tabla!$L$99,Tabla!$L$99,IF(O7=Tabla!$L$100,Tabla!$L$100,IF(O7=Tabla!$L$101,Tabla!$L$101,IF(O7=Tabla!$L$102,Tabla!$L$102,IF(O7=Tabla!$L$103,Tabla!$L$103,IF(O7=Tabla!$L$104,Tabla!$L$104,IF(O7=Tabla!$L$105,Tabla!$L$105,"NO DISPBLE"))))))))))))))))))) -> 44 | O9: cm | P9: Cambios | R9: 0 | S9: 100
B10: Ancho Lamina | D10: =+D9+3 -> 44 | F10: cm | G10: Bilaminación Scrap | J10: 0 | K10: cm | L10: Mangas Disp | N10: 35 | O10: cm | P10: Colores | R10: 4 | S10: =+R10*(R8+R9) -> 4
G11: Extras | J11: NO | K11: U$S | L11: 0 | P11: % Impreso | R11: 100 | S11: Flete | T11: 1
G12: Valor por Millar al contado | P12: U$S | Q12: =+R49 -> 637.38632 | S12: Caba | T12: 900
G13: Valor por Kgrs a | K13: 30 | L13: días FF | N13: =INDEX(Tabla!$B$199:$B$202,MATCH(K13,Tabla!$A$199:$A$202,0))/100 -> 0.041666667 | P13: U$S | Q13: =+R50 -> 663.94408 | S13: =+((Q13*J4)/1000)/J6 -> 147.62934 | T13: xKg
B15: Detalle | E15: Mic | F15: Valor x Kgrs (U$S) | H15: Mtrs a trabajar | J15: Kgrs a trabajar | K15: Kgrs x 1000 Mts | L15: Kgrs x 1000 Mts | M15: Valor x 1000 mts | O15: Valor Kgrs | Q15: Valor x Millar | S15: Incidencia
A16: 1 | B16: =+D4 -> PoliesterCristal | E16: =+F4 -> 12 | F16: =(IF(B16=Tabla!$A$16,Tabla!$D$16,IF(B16=Tabla!$A$17,Tabla!$D$17,IF(B16=Tabla!$A$18,Tabla!$D$18,IF(B16=Tabla!$A$19,Tabla!$D$19,IF(B16=Tabla!$A$20,Tabla!$D$20,IF(B16=Tabla!$A$21,Tabla!$D$21,IF(B16=Tabla!$A$22,Tabla!$D$22,IF(B16=Tabla!$A$23,Tabla!$D$23,IF(B16=Tabla!$A$24,Tabla!$D$24,IF(B16=Tabla!$A$25,Tabla!$D$25,IF(B16=Tabla!$A$26,Tabla!$D$26,IF(B16=Tabla!$A$27,Tabla!$D$27,IF(B16=Tabla!$A$28,Tabla!$D$28,IF(B16=Tabla!$A$29,Tabla!$D$29,IF(B16=Tabla!$A$30,Tabla!$D$30,IF(B16=Tabla!$A$31,Tabla!$D$31,IF(B16=Tabla!$A$32,Tabla!$D$32,IF(B16=Tabla!$A$33,Tabla!$D$33)))))))))))))))))))*A16 -> 3.65 | H16: =+J5+(1500*(R8+R9)) -> 1830 | J16: =(IF(B16=Tabla!$A$16,Tabla!$C$16,IF(B16=Tabla!$A$17,Tabla!$C$17,IF(B16=Tabla!$A$18,Tabla!$C$18,IF(B16=Tabla!$A$19,Tabla!$C$19,IF(B16=Tabla!$A$20,Tabla!$C$20,IF(B16=Tabla!$A$21,Tabla!$C$21,IF(B16=Tabla!$A$22,Tabla!$C$22,IF(B16=Tabla!$A$23,Tabla!$C$23,IF(B16=Tabla!$A$24,Tabla!$C$24,IF(B16=Tabla!$A$25,Tabla!$C$25,IF(B16=Tabla!$A$26,Tabla!$C$26,IF(B16=Tabla!$A$27,Tabla!$C$27,IF(B16=Tabla!$A$28,Tabla!$C$28,IF(B16=Tabla!$A$29,Tabla!$C$29,IF(B16=Tabla!$A$30,Tabla!$C$30,IF(B16=Tabla!$A$31,Tabla!$C$31,IF(B16=Tabla!$A$32,Tabla!$C$32,IF(B16=Tabla!$A$33,Tabla!$C$33,””)))))))))))))))))))*(H16/1000)*((D10+J8)/100)*E16 -> 13.623984 | K16: =(IF(B16=Tabla!$A$16,Tabla!$C$16,IF(B16=Tabla!$A$17,Tabla!$C$17,IF(B16=Tabla!$A$18,Tabla!$C$18,IF(B16=Tabla!$A$19,Tabla!$C$19,IF(B16=Tabla!$A$20,Tabla!$C$20,IF(B16=Tabla!$A$21,Tabla!$C$21,IF(B16=Tabla!$A$22,Tabla!$C$22,IF(B16=Tabla!$A$23,Tabla!$C$23,IF(B16=Tabla!$A$24,Tabla!$C$24,IF(B16=Tabla!$A$25,Tabla!$C$25,IF(B16=Tabla!$A$26,Tabla!$C$26,IF(B16=Tabla!$A$27,Tabla!$C$27,IF(B16=Tabla!$A$28,Tabla!$C$28,IF(B16=Tabla!$A$29,Tabla!$C$29,IF(B16=Tabla!$A$30,Tabla!$C$30,IF(B16=Tabla!$A$31,Tabla!$C$31,IF(B16=Tabla!$A$32,Tabla!$C$32,IF(B16=Tabla!$A$33,Tabla!$C$33,””)))))))))))))))))))*E16*((D10+J8)/100) -> 7.4448 | L16: =(IF(B16=Tabla!$A$16,Tabla!$C$16,IF(B16=Tabla!$A$17,Tabla!$C$17,IF(B16=Tabla!$A$18,Tabla!$C$18,IF(B16=Tabla!$A$19,Tabla!$C$19,IF(B16=Tabla!$A$20,Tabla!$C$20,IF(B16=Tabla!$A$21,Tabla!$C$21,IF(B16=Tabla!$A$22,Tabla!$C$22,IF(B16=Tabla!$A$23,Tabla!$C$23,IF(B16=Tabla!$A$24,Tabla!$C$24,IF(B16=Tabla!$A$25,Tabla!$C$25,IF(B16=Tabla!$A$26,Tabla!$C$26,IF(B16=Tabla!$A$27,Tabla!$C$27,IF(B16=Tabla!$A$28,Tabla!$C$28,IF(B16=Tabla!$A$29,Tabla!$C$29,IF(B16=Tabla!$A$30,Tabla!$C$30,IF(B16=Tabla!$A$31,Tabla!$C$31,IF(B16=Tabla!$A$32,Tabla!$C$32,IF(B16=Tabla!$A$33,Tabla!$C$33,””)))))))))))))))))))*E16*(D9/100) -> 6.9372 | M16: U$S | N16: =((J16*F16)/(J5/1000)) -> 150.68952 | O16: U$S | P16: =N16/(SUM(L16:L18)) -> 3.685674 | Q16: U$S | R16: =IF(R6>1,((+N16/(100/D3))/R6),+N16/(100/D3)) -> 16.575847 | S16: =(R16*100)/(Q12-R43-R44) -> 6.1028962 | T16: %
A17: 1 | B17: =+D5 -> PolietilenoDpk | E17: =+F5 -> 90 | F17: =(IF(B17=Tabla!$A$16,Tabla!$D$16,IF(B17=Tabla!$A$17,Tabla!$D$17,IF(B17=Tabla!$A$18,Tabla!$D$18,IF(B17=Tabla!$A$19,Tabla!$D$19,IF(B17=Tabla!$A$20,Tabla!$D$20,IF(B17=Tabla!$A$21,Tabla!$D$21,IF(B17=Tabla!$A$22,Tabla!$D$22,IF(B17=Tabla!$A$23,Tabla!$D$23,IF(B17=Tabla!$A$24,Tabla!$D$24,IF(B17=Tabla!$A$25,Tabla!$D$25,IF(B17=Tabla!$A$26,Tabla!$D$26,IF(B17=Tabla!$A$27,Tabla!$D$27,IF(B17=Tabla!$A$28,Tabla!$D$28,IF(B17=Tabla!$A$29,Tabla!$D$29,IF(B17=Tabla!$A$30,Tabla!$D$30,IF(B17=Tabla!$A$31,Tabla!$D$31,IF(B17=Tabla!$A$32,Tabla!$D$32,IF(B17=Tabla!$A$33,Tabla!$D$33)))))))))))))))))))*A17 -> 3.3235674 | H17: =+J5+100 -> 430 | J17: =(IF(B17=Tabla!$A$16,Tabla!$C$16,IF(B17=Tabla!$A$17,Tabla!$C$17,IF(B17=Tabla!$A$18,Tabla!$C$18,IF(B17=Tabla!$A$19,Tabla!$C$19,IF(B17=Tabla!$A$20,Tabla!$C$20,IF(B17=Tabla!$A$21,Tabla!$C$21,IF(B17=Tabla!$A$22,Tabla!$C$22,IF(B17=Tabla!$A$23,Tabla!$C$23,IF(B17=Tabla!$A$24,Tabla!$C$24,IF(B17=Tabla!$A$25,Tabla!$C$25,IF(B17=Tabla!$A$26,Tabla!$C$26,IF(B17=Tabla!$A$27,Tabla!$C$27,IF(B17=Tabla!$A$28,Tabla!$C$28,IF(B17=Tabla!$A$29,Tabla!$C$29,IF(B17=Tabla!$A$30,Tabla!$C$30,IF(B17=Tabla!$A$31,Tabla!$C$31,IF(B17=Tabla!$A$32,Tabla!$C$32,IF(B17=Tabla!$A$33,Tabla!$C$33,””)))))))))))))))))))*(H17/1000)*((D10+J9)/100)*E17 -> 15.66576 | K17: =(IF(B17=Tabla!$A$16,Tabla!$C$16,IF(B17=Tabla!$A$17,Tabla!$C$17,IF(B17=Tabla!$A$18,Tabla!$C$18,IF(B17=Tabla!$A$19,Tabla!$C$19,IF(B17=Tabla!$A$20,Tabla!$C$20,IF(B17=Tabla!$A$21,Tabla!$C$21,IF(B17=Tabla!$A$22,Tabla!$C$22,IF(B17=Tabla!$A$23,Tabla!$C$23,IF(B17=Tabla!$A$24,Tabla!$C$24,IF(B17=Tabla!$A$25,Tabla!$C$25,IF(B17=Tabla!$A$26,Tabla!$C$26,IF(B17=Tabla!$A$27,Tabla!$C$27,IF(B17=Tabla!$A$28,Tabla!$C$28,IF(B17=Tabla!$A$29,Tabla!$C$29,IF(B17=Tabla!$A$30,Tabla!$C$30,IF(B17=Tabla!$A$31,Tabla!$C$31,IF(B17=Tabla!$A$32,Tabla!$C$32,IF(B17=Tabla!$A$33,Tabla!$C$33,””)))))))))))))))))))*E17*((D10+J8)/100) -> 36.432 | L17: =(IF(B17=Tabla!$A$16,Tabla!$C$16,IF(B17=Tabla!$A$17,Tabla!$C$17,IF(B17=Tabla!$A$18,Tabla!$C$18,IF(B17=Tabla!$A$19,Tabla!$C$19,IF(B17=Tabla!$A$20,Tabla!$C$20,IF(B17=Tabla!$A$21,Tabla!$C$21,IF(B17=Tabla!$A$22,Tabla!$C$22,IF(B17=Tabla!$A$23,Tabla!$C$23,IF(B17=Tabla!$A$24,Tabla!$C$24,IF(B17=Tabla!$A$25,Tabla!$C$25,IF(B17=Tabla!$A$26,Tabla!$C$26,IF(B17=Tabla!$A$27,Tabla!$C$27,IF(B17=Tabla!$A$28,Tabla!$C$28,IF(B17=Tabla!$A$29,Tabla!$C$29,IF(B17=Tabla!$A$30,Tabla!$C$30,IF(B17=Tabla!$A$31,Tabla!$C$31,IF(B17=Tabla!$A$32,Tabla!$C$32,IF(B17=Tabla!$A$33,Tabla!$C$33,””)))))))))))))))))))*E17*(D9/100) -> 33.948 | M17: U$S | N17: =((J17*F17)/(J5/1000)) -> 157.77639 | O17: U$S | P17: =N17/(SUM(L16:L18)) -> 3.8590099 | Q17: U$S | R17: =IF(R6>1,((+N17/(100/D3))/R6),+N17/(100/D3)) -> 17.355403 | S17: =(R17*100)/(Q12-R43-R44) -> 6.389913 | T17: %
A18: 1 | B18: =+D6 -> Otro | E18: =+F6 -> 0 | F18: =(IF(B18=Tabla!$A$16,Tabla!$D$16,IF(B18=Tabla!$A$17,Tabla!$D$17,IF(B18=Tabla!$A$18,Tabla!$D$18,IF(B18=Tabla!$A$19,Tabla!$D$19,IF(B18=Tabla!$A$20,Tabla!$D$20,IF(B18=Tabla!$A$21,Tabla!$D$21,IF(B18=Tabla!$A$22,Tabla!$D$22,IF(B18=Tabla!$A$23,Tabla!$D$23,IF(B18=Tabla!$A$24,Tabla!$D$24,IF(B18=Tabla!$A$25,Tabla!$D$25,IF(B18=Tabla!$A$26,Tabla!$D$26,IF(B18=Tabla!$A$27,Tabla!$D$27,IF(B18=Tabla!$A$28,Tabla!$D$28,IF(B18=Tabla!$A$29,Tabla!$D$29,IF(B18=Tabla!$A$30,Tabla!$D$30,IF(B18=Tabla!$A$31,Tabla!$D$31,IF(B18=Tabla!$A$32,Tabla!$D$32,IF(B18=Tabla!$A$33,Tabla!$D$33)))))))))))))))))))*A18 -> 0 | H18: =+J5+100 -> 430 | J18: =(IF(B18=Tabla!$A$16,Tabla!$C$16,IF(B18=Tabla!$A$17,Tabla!$C$17,IF(B18=Tabla!$A$18,Tabla!$C$18,IF(B18=Tabla!$A$19,Tabla!$C$19,IF(B18=Tabla!$A$20,Tabla!$C$20,IF(B18=Tabla!$A$21,Tabla!$C$21,IF(B18=Tabla!$A$22,Tabla!$C$22,IF(B18=Tabla!$A$23,Tabla!$C$23,IF(B18=Tabla!$A$24,Tabla!$C$24,IF(B18=Tabla!$A$25,Tabla!$C$25,IF(B18=Tabla!$A$26,Tabla!$C$26,IF(B18=Tabla!$A$27,Tabla!$C$27,IF(B18=Tabla!$A$28,Tabla!$C$28,IF(B18=Tabla!$A$29,Tabla!$C$29,IF(B18=Tabla!$A$30,Tabla!$C$30,IF(B18=Tabla!$A$31,Tabla!$C$31,IF(B18=Tabla!$A$32,Tabla!$C$32,IF(B18=Tabla!$A$33,Tabla!$C$33,””)))))))))))))))))))*(H18/1000)*((D10+J10)/100)*E18 -> 0 | K18: =(IF(B18=Tabla!$A$16,Tabla!$C$16,IF(B18=Tabla!$A$17,Tabla!$C$17,IF(B18=Tabla!$A$18,Tabla!$C$18,IF(B18=Tabla!$A$19,Tabla!$C$19,IF(B18=Tabla!$A$20,Tabla!$C$20,IF(B18=Tabla!$A$21,Tabla!$C$21,IF(B18=Tabla!$A$22,Tabla!$C$22,IF(B18=Tabla!$A$23,Tabla!$C$23,IF(B18=Tabla!$A$24,Tabla!$C$24,IF(B18=Tabla!$A$25,Tabla!$C$25,IF(B18=Tabla!$A$26,Tabla!$C$26,IF(B18=Tabla!$A$27,Tabla!$C$27,IF(B18=Tabla!$A$28,Tabla!$C$28,IF(B18=Tabla!$A$29,Tabla!$C$29,IF(B18=Tabla!$A$30,Tabla!$C$30,IF(B18=Tabla!$A$31,Tabla!$C$31,IF(B18=Tabla!$A$32,Tabla!$C$32,IF(B18=Tabla!$A$33,Tabla!$C$33,””)))))))))))))))))))*E18*((D10+J8)/100) -> 0 | L18: =(IF(B18=Tabla!$A$16,Tabla!$C$16,IF(B18=Tabla!$A$17,Tabla!$C$17,IF(B18=Tabla!$A$18,Tabla!$C$18,IF(B18=Tabla!$A$19,Tabla!$C$19,IF(B18=Tabla!$A$20,Tabla!$C$20,IF(B18=Tabla!$A$21,Tabla!$C$21,IF(B18=Tabla!$A$22,Tabla!$C$22,IF(B18=Tabla!$A$23,Tabla!$C$23,IF(B18=Tabla!$A$24,Tabla!$C$24,IF(B18=Tabla!$A$25,Tabla!$C$25,IF(B18=Tabla!$A$26,Tabla!$C$26,IF(B18=Tabla!$A$27,Tabla!$C$27,IF(B18=Tabla!$A$28,Tabla!$C$28,IF(B18=Tabla!$A$29,Tabla!$C$29,IF(B18=Tabla!$A$30,Tabla!$C$30,IF(B18=Tabla!$A$31,Tabla!$C$31,IF(B18=Tabla!$A$32,Tabla!$C$32,IF(B18=Tabla!$A$33,Tabla!$C$33,””)))))))))))))))))))*E18*(D9/100) -> 0 | M18: U$S | N18: =((J18*F18)/(J5/1000)) -> 0 | O18: U$S | P18: =N18/(SUM(L16:L18)) -> 0 | Q18: U$S | R18: =IF(R6>1,((+N18/(100/D3))/R6),+N18/(100/D3)) -> 0 | S18: =(R18*100)/(Q12-R43-R44) -> 0 | T18: %
A19: =IF(D7="SI",1,0) -> 1 | B19: Costo Impresora | E19: Prep | F19: Prod | G19: Prep | H19: SobreImpresion | J19: Valor Hs
A20: =IF(F7="SI",1,0) -> 1 | B20: Reprint | E20: =(Tabla!$D$5*R8+1*R9)*A19 -> 1.5 | F20: =(+J5/20000)*A19 -> 0.0165 | G20: =(Tabla!$D$5/3)*A20 -> 0.5 | H20: =(J5/20000)*A20 -> 0.0165 | J20: U$S | K20: =+Tabla!$B$5 -> 58.46 | M20: U$S | N20: =((E20+F20+G20+H20)*K20)/(J5/1000)*A19 -> 360.14903 | O20: U$S | P20: =N20/(SUM(L16:L18)) -> 8.8087873 | Q20: U$S | R20: =IF(R6>1,((+N20/(100/D3))/R6),+N20/(100/D3)) -> 39.616393 | S20: =(R20*100)/(Q12-R43-R44) -> 14.585965 | T20: %
A21: =IF(D7="SI",1,0) -> 1 | B21: Tela Doble Fax | I21: =(+L21/S10)*A20 -> 1.3689698 | J21: x Color U$S | L21: =(IF(B21=Tabla!$A$79,((Tabla!$B$79/2300/46)*(D10+J8)*N9),1)*0.75) -> 5.475879 | O21: U$S | P21: =((I21+L21*S10)/J6)*A21 -> 1.7248952 | Q21: U$S | R21: =IF(R6>1,((((I21+L21*R10)/(J4/1000)*A21))/R6),((I21+L21*R10)/(J4/1000)*A21)) -> 7.7574953 | S21: =(R21*100)/(Q12-R43-R44) -> 2.856155 | T21: %
A22: =IF(D7="SI",1,0) -> 1 | B22: Tintas + Diluyentes | I22: =(((Tabla!$B$90*0.8)+(Tabla!$B$93*0.2))/1000*2)*A20 -> 0.009368 | J22: Valor grs/mts2 | L22: =(((((Tabla!$J$116-Tabla!$E$116)/1000*2)+((Tabla!$E$116/1000*2)*S9)/100)*R11)/100)+I22 -> 0.040079123 | M22: U$S | N22: =(L22*((D10+J8)*10)*A22)*(R10/8) -> 8.8174071 | O22: U$S | P22: =N22/(SUM(L16:L18)) -> 0.21566257 | Q22: U$S | R22: =IF(R6>1,((+N22/(100/D3))/R6),+N22/(100/D3)) -> 0.96991478 | S22: =(R22*100)/(Q12-R43-R44) -> 0.35710327 | T22: %
A23: =IF(D7="SI",1,0) -> 1 | B23: Limpieza Diluyentes | E23: =IF(J5>240000,120,IF(J5>210000,96,IF(J5>180000,72,IF(J5>150000,64,IF(J5>120000,48,IF(J5>60000,24,IF(J5>30000,16,12))))))) -> 12 | J23: Valor Lts | L23: =+Tabla!$B$99 -> 1.25 | M23: U$S | N23: =(+L23*E23/J5*1000)*A23 -> 45.454545 | O23: U$S | P23: =N23/(SUM(L16:L18)) -> 1.1117604 | Q23: U$S | R23: =IF(R6>1,((+N23/(100/D3))/R6),+N23/(100/D3)) -> 5 | S23: =(R23*100)/(Q12-R43-R44) -> 1.8409002 | T23: %
A24: =IF(J7="SI",1,IF(J7="BI",2,0)) -> 1 | B24: Costo Laminado | E24: =+Tabla!$D$6*(A24+A26) -> 1 | F24: =+J5/Tabla!$C$6*(A25+A26) -> 0.04125 | J24: U$S | K24: =+Tabla!$B$6 -> 41.35 | M24: U$S | N24: =((E24+F24)*K24)/(J5/1000) -> 130.47178 | O24: U$S | P24: =N24/(SUM(L16:L18)) -> 3.1911738 | Q24: U$S | R24: =IF(R6>1,((+N24/(100/D3))/R6),+N24/(100/D3)) -> 14.351896 | S24: =(R24*100)/(Q12-R43-R44) -> 5.2840817 | T24: %
A25: =IF(J7="SI",1,IF(J7="BI",2,0)) -> 1 | B25: Solvent Less | J25: Valor grs/mts2 | L25: =IF(J7="SI",+(((Tabla!$B$123/1000*Tabla!$C$123)+(Tabla!$B$124/1000*Tabla!C350))*Tabla!$B$122)*A25,IF(J7="BI",+(((Tabla!$B$123/1000*Tabla!$C$123)+(Tabla!$B$124/1000*Tabla!C350))*Tabla!$B$122)*A25,0)) -> 0.012474 | M25: U$S | N25: =L25*((D10+J9+J10)*10) -> 5.48856 | O25: U$S | P25: =N25/(SUM(L16:L18)) -> 0.1342432 | Q25: U$S | R25: =IF(R6>1,((+N25/(100/D3))/R6),+N25/(100/D3)) -> 0.6037416 | S25: =(R25*100)/(Q12-R43-R44) -> 0.22228561 | T25: %
A26: =IF(N7="SI",1,IF(N7="BI",2,0)) -> 1 | B26: Solvent | J26: Valor grs/mts2 | L26: =IF(N7="SI",+((Tabla!$B$127/1000)*Tabla!$B$126)*A26,IF(N7="BI",+((Tabla!$B$127/1000)*Tabla!$B$126)*A26,0)) -> 0.04452 | M26: U$S | N26: =L26*(D10*10) -> 19.5888 | O26: U$S | P26: =N26/(SUM(L16:L18)) -> 0.47911714 | Q26: U$S | R26: =IF(R6>1,((+N26/(100/D3))/R6),+N26/(100/D3)) -> 2.154768 | S26: =(R26*100)/(Q12-R43-R44) -> 0.79334258 | T26: %
B27: Refilado | E27: =+Tabla!$D$7 -> 0 | F27: =+J5/Tabla!$C$7 -> 0.04125 | J27: U$S | K27: =+Tabla!$B$7 -> 39.54 | M27: U$S | N27: =((E27+F27)*K27)/(J5/1000) -> 4.9425 | O27: U$S | P27: =N27/(SUM(L16:L18)) -> 0.12088726 | Q27: U$S | R27: =IF(R6>1,((+N27/(100/D3))/R6),+N27/(100/D3)) -> 0.543675 | S27: =(R27*100)/(Q12-R43-R44) -> 0.20017029 | T27: %
A28: =+Tabla!$E$7 -> 0.05 | B28: % Material Scrap | M28: U$S | N28: =((SUM(P16:P27))*A28) -> 1.1665605 | O28: U$S | P28: =((SUM(P16:P27))*A28) -> 1.1665605 | Q28: U$S | R28: =+N28/(100/D3) -> 0.12832166 | S28: =(R28*100)/(Q12-R43-R44) -> 0.047245474 | T28: %
B29: Costo Bobina | O29: U$S | P29: =SUM(P16:P28) -> 24.497771
A30: =IF(D3>=38,Tabla!$E$155,IF(D3>=25,Tabla!$E$150,IF(D3>=18,Tabla!$E$147,IF(D3>=15,Tabla!$E$144,Tabla!$E$139))))-(A31*Tabla!$G$139) -> 65 | B30: Costo Confeccionadora | E30: 1 | F30: =+J4/+(A30*60) -> 0.76923077 | J30: U$S | K30: =+Tabla!$B$8 -> 60.01 | L30: =+(((+E30+F30)*K30)/J4)*1000 -> 35.390513 | M30: U$S | N30: =((E30+F30)*K30)/(J5/1000) -> 321.73193 | O30: U$S | P30: =N30/(SUM(L16:L18)) -> 7.869154 | Q30: U$S | R30: =+N30/(100/D3) -> 35.390513 | S30: =(R30*100)/(Q12-R43-R44) -> 13.030081 | T30: %
A31: =IF(S3="SI",1,0) -> 1 | B31: Zipper | E31: Scrap | F31: =+Tabla!$F$8 -> 100 | M31: U$S | N31: =+Tabla!$B$132*(1000+F31)*A31 -> 47.194719 | O31: U$S | P31: =N31/(SUM(L16:L18)) -> 1.1543228 | Q31: U$S | R31: =+N31/(100/D3) -> 5.1914191 | S31: =(R31*100)/(Q12-R43-R44) -> 1.9113769 | T31: %
A32: =IF(S4="SI",1,0) -> 1 | B32: Troquel | E32: Scrap | F32: =+Tabla!$F$8 -> 100 | M32: U$S | N32: =+Tabla!$E$132*(1000+F32)*A32 -> 16.5 | O32: U$S | P32: =N32/(SUM(L16:L18)) -> 0.40356902 | Q32: U$S | R32: =+Tabla!$E$132*(1000+F32)*A32 -> 16.5 | S32: =(R32*100)/(Q12-R43-R44) -> 6.0749707 | T32: %
A33: =+Tabla!$E$8 -> 0.15 | B33: Scrap Confeccionadora | M33: U$S | N33: =+(P29*A33)/(100000/D3)*1000 -> 0.40421323 | O33: U$S | P33: =N33/(SUM(L16:L18)) -> 0.0098865415 | Q33: U$S | R33: =SUM(R16:R31)*A33 -> 21.845908 | S33: =(R33*100)/(Q12-R43-R44) -> 8.0432274 | T33: %
A34: =+Tabla!$C$10 -> 20 | B34: Costo Picotera | E34: =+Tabla!$D$10 -> 0.5 | F34: =+J4/+(A34*60) -> 2.5 | J34: U$S | K34: =+Tabla!$B$10 -> 20.003333 | L34: =+(((+E34+F34)*K34)/J4)*1000 -> 20.003333 | M34: U$S | N34: =((E34+F34)*K34)/(J5/1000) -> 181.84848 | O34: U$S | P34: =N34/(SUM(L16:L18)) -> 4.4477827 | Q34: U$S | R34: =+N34/(100/D3)*A35 -> 20.003333 | S34: =(R34*100)/(Q12-R43-R44) -> 7.3648282 | T34: %
A35: =IF(S5="SI",1,0) -> 1 | B35: Picos | E35: Scrap | F35: =+Tabla!$F$10 -> 100 | M35: U$S | N35: =+Tabla!$E$133*(1000+F35)*A35 -> 35.454888 | O35: U$S | P35: =N35/(SUM(L16:L18)) -> 0.86718147 | Q35: U$S | R35: =+Tabla!$E$133*(1000+F35)*A35 -> 35.454888 | S35: =(R35*100)/(Q12-R43-R44) -> 13.053782 | T35: %
A36: =+Tabla!$E$10 -> 0.05 | B36: Scrap Picotera | M36: U$S | N36: =+(P29*A36)/(100000/D3)*1000 -> 0.13473774 | O36: U$S | P36: =N36/(SUM(L16:L18)) -> 0.0032955138 | Q36: U$S | R36: =SUM(R16:R35)*A36*A35 -> 11.972176 | S36: =(R36*100)/(Q12-R43-R44) -> 4.4079162 | T36: %
A37: =IF(D3>22.1,400,IF(D3>=15,1000,IF(D3>=12,1500,2000))) -> 2000 | B37: x Caja | M37: U$S | N37: =+Tabla!$B$133/A37*1000 -> 0.18822112 | O37: U$S | P37: =N37/(SUM(L16:L18)) -> 0.0046036493 | Q37: U$S | R37: =1000/A37*N37 -> 0.094110561 | S37: =(R37*100)/(Q12-R43-R44) -> 0.034649631 | T37: %
A38: =+T11 -> 1 | B38: Flete | D38: =+S12 -> Caba | E38: =+T12 -> 900 | F38: =INDEX(Tabla!$B$162:$E$187,MATCH(S12,Tabla!$A$162:$A$187,0),MATCH(T12,Tabla!$B$161:$E$161,0))*A38 -> 57.182178 | O38: U$S | P38: =F38/(SUM(J6)) -> 4.238192 | Q38: U$S | R38: =+J6*P38/J4*1000 -> 19.060726 | S38: =(R38*100)/(Q12-R43-R44) -> 7.017779 | T38: %
A39: =IF(J11="SI",1,0) -> 0 | B39: Extras | O39: U$S | P39: =(+L11/J6)*A39 -> 0 | Q39: U$S | R39: =(+L11/J4)*A39 -> 0 | S39: =(R39*100)/(Q12-R43-R44) -> 0 | T39: %
B40: Costo Envase | O40: U$S | P40: =SUM(P30:P39) -> 18.997988 | S40: =(SUM(R20,R24,R27,R30)+SUM(A42:A44)+E43)/100 -> 1.5303548 | T40: Costo Produc
A41: Rentabilidad | K41: Financiado | L41: Costo Bruto | O41: U$S | P41: =+P40+P29 -> 43.495759 | Q41: U$S | R41: =SUM(R16:R39)+(R45*A45) -> 270.57053 | S41: Costo Financiación Bancaria
A42: =IF(AND(D3<=18,J6<=Tabla!$B$217),Tabla!$B$218,IF(AND(D3<=18,J6<=Tabla!$C$217),Tabla!$C$218,IF(AND(D3<=18,J6<=Tabla!$D$217),Tabla!$D$218,IF(AND(D3<=18,J6<=Tabla!$E$217),Tabla!$E$218,IF(AND(D3<=18,J6<=Tabla!$F$217),Tabla!$F$218,IF(AND(D3<=18,J6<=Tabla!$G$217),Tabla!$G$218,IF(AND(D3<=18,J6<=Tabla!$H$217),Tabla!$H$218,IF(AND(D3<=18,J6<=Tabla!$I$217),Tabla!$I$218,IF(AND(D3>=18,J6<=Tabla!$B$217),Tabla!$B$220,IF(AND(D3>=18,J6<=Tabla!$C$217),Tabla!$C$220,IF(AND(D3>=18,J6<=Tabla!$D$217),Tabla!$D$220,IF(AND(D3>=18,J6<=Tabla!$E$217),Tabla!$E$220,IF(AND(D3>=18,J6<=Tabla!$F$217),Tabla!$F$220,IF(AND(D3>=18,J6<=Tabla!$G$217),Tabla!$G$220,IF(AND(D3>=18,J6<=Tabla!$H$217),Tabla!$H$220,Tabla!$I$220))))))))))))))) -> 51.3 | B42: % Plus | C42: Cliente | E42: =+K1 -> A | F42: U$S | G42: =+I42*J6 -> 891.66605 | I42: =+((((R42*J4)/1000)/J6)) -> 66.087932 | J42: xKg | K42: =+((((T44*J4)/1000)/J6)) -> 72.366613 | L42: Rentabilidad Bobina | O42: U$S | P42: =(P46*(A42/100)) -> 47.780138 | Q42: U$S | R42: =(R46*(A42/100)) -> 297.22202 | S42: U$S | T42: =+R50-R48 -> 27.59348
A43: =IF(K1="A",Tabla!$J$217,IF(K1="B",Tabla!$K$217,IF(K1="C",Tabla!$L$217,Tabla!$M$217))) -> 0 | B43: % | C43: Ajuste | E43: =+N1 -> 9.833 | F43: U$S | G43: =+I43*J6 -> 1059.1592 | I43: =+((((R43*J4)/1000)/J6)) -> 78.50208 | J43: xKg | K43: =K42*J6 -> 976.37873 | L43: Confección | O43: U$S | P43: =+P48-P41-P44 -> 56.938463 | Q43: U$S | R43: =+R48-R41-R44 -> 353.05306 | S43: Rentabilidad Bonificando
A44: =IF(S1="AK",Tabla!$B$191,IF(S1="PM",Tabla!$B$192,IF(S1="4P",Tabla!$B$193,Tabla!$B$194)))+T2 -> 2 | B44: % Comision | E44: =+S1 -> AK | F44: U$S | G44: =+I44*J6 -> 38.181036 | I44: =+(((R44*J4)/1000)/J6) -> 2.8298775 | J44: xKg | K44: Bonificación | L44: U$S | M44: =+I43-P43 -> 21.563617 | O44: U$S | P44: =+P46*(A44/100) -> 1.8627734 | Q44: U$S | R44: =+R48*(A44/100) -> 12.727012 | S44: U$S | T44: =+R43-T42 -> 325.45958
A45: 0 | B45: Costo Polímeros | E45: 1 | F45: U$S | G45: =+(D10*(N9+3)*S10*0.055) -> 454.96 | I45: =+G45/J6 -> 33.720433 | J45: xKg | K45: =+G43-K43 -> 82.780441 | O45: U$S | P45: =+I45*A45 -> 0 | Q45: U$S | R45: =(+J6*I45/J4*1000)*A45 -> 0
B46: Rentabilidad Bonificando Polímeros | F46: U$S | G46: =+I46*J6 -> 1059.1592 | I46: =I43-(I45*E45*A45) -> 78.50208 | J46: xKg | O46: U$S | P46: =+P41/(1-((A42+A44)/100)) -> 93.13867 | Q46: U$S | R46: =+R41/(1-((A42+A44)/100)) -> 579.38015
O47: U$S | P47: =+P46*(E43/100) -> 9.1583254 | Q47: U$S | R47: =+R46*(E43/100) -> 56.97045
F48: Valor por Millar al contado | O48: U$S | P48: =+P46+P47 -> 102.297 | Q48: U$S | R48: =+R46+R47 -> 636.3506
Q49: U$S | R49: =(+R41/(1-((A42+(A44+(A44*N13)))/100)))+R46*(E43/100) -> 637.38632
F50: Valor por Kgrs a | J50: =+K13 -> 30 | K50: días FF | M50: =+N13 -> 0.041666667 | O50: U$S | P50: =+(P48*M50)+P48 -> 106.55937 | Q50: U$S | R50: =+(R49*M50)+R49 -> 663.94408

Sheet Confeccion Pouch
A1: 4PACK | C1: Cliente | K1: A | L1: Ajuste | N1: 0 | Q1: Vendedor | S1: AK
A2: DOYPACK | C2: Pouch | K2: Nro. de Cotizacion: | O2: / 2025 | Q2: =TODAY() -> 46286 | S2: Ajuste | T2: 0
B3: Ancho | D3: 25 | F3: cm | G3: Alto | J3: 34 | K3: cm | Q3: ZIPPER | S3: NO
A4: Proveedor | B4: Vitopel | D4: PoliesterCristal | F4: 12 | G4: mic | H4: Envases | J4: 50000 | K4: unidades | R4: TROQUEL | S4: NO
B5: Ingepol | D5: PolietilenoDpk | F5: 200 | G5: mic | H5: Cantidad | J5: =+J4*D3/100 -> 12500 | K5: mts | R5: PICO | S5: NO
B6: Otro | D6: Otro | F6: 0 | G6: mic | H6: Peso | J6: =(SUM(L16:L18))*(J5/1000) -> 1707.82 | K6: Kgrs | P6: Modulos en el Ancho | R6: 1 | S6: Calle Interna entre Modulos
B7: IMPRESIÓN | D7: SI | E7: RePRINT | F7: NO | G7: LAMINACION SIN SOLVENTE | J7: SI | K7: CON SOLVENTE | N7: NO | O7: =+N8*R7 -> 50 | P7: Modulos Desarrollo | R7: 2 | S7: 0
B8: Ancho | D8: =(+J3*2) -> 68 | F8: cm | G8: Impresión Scrap | J8: 0 | K8: cm | L8: Paso | N8: =+D3 -> 25 | O8: cm | P8: Diseños | R8: 1 | S8: Blanco %
B9: Ancho Refilado | D9: =(+D8*R6)+S7 -> 68 | F9: cm | G9: Laminación Scrap | J9: 0 | K9: cm | L9: Desarrollo | N9: =IF(O7=Tabla!$L$87,Tabla!$L$87,IF(O7=Tabla!$L$88,Tabla!$L$88,IF(O7=Tabla!$L$89,Tabla!$L$89,IF(O7=Tabla!$L$90,Tabla!$L$90,IF(O7=Tabla!$L$91,Tabla!$L$91,IF(O7=Tabla!$L$92,Tabla!$L$92,IF(O7=Tabla!$L$93,Tabla!$L$93,IF(O7=Tabla!$L$94,Tabla!$L$94,IF(O7=Tabla!$L$95,Tabla!$L$95,IF(O7=Tabla!$L$96,Tabla!$L$96,IF(O7=Tabla!$L$97,Tabla!$L$97,IF(O7=Tabla!$L$98,Tabla!$L$98,IF(O7=Tabla!$L$99,Tabla!$L$99,IF(O7=Tabla!$L$100,Tabla!$L$100,IF(O7=Tabla!$L$101,Tabla!$L$101,IF(O7=Tabla!$L$102,Tabla!$L$102,IF(O7=Tabla!$L$103,Tabla!$L$103,IF(O7=Tabla!$L$104,Tabla!$L$104,IF(O7=Tabla!$L$105,Tabla!$L$105,"NO DISPBLE"))))))))))))))))))) -> 50 | O9: cm | P9: Cambios | R9: 0 | S9: 100
B10: Ancho Lamina | D10: =+D9+3 -> 71 | F10: cm | G10: Bilaminación Scrap | J10: 0 | K10: cm | L10: Mangas Disp | N10: 35 | O10: cm | P10: Colores | R10: 8 | S10: =+R10*(R8+R9) -> 8
G11: Extras | J11: NO | K11: U$S | L11: 0 | P11: % Impreso | R11: 100 | S11: Flete | T11: 1
G12: Valor por Millar al contado | P12: U$S | Q12: =+R49 -> 297.68871 | S12: Caba | T12: 900
G13: Valor por Kgrs a | K13: 45 | L13: días FF | N13: =INDEX(Tabla!$B$199:$B$202,MATCH(K13,Tabla!$A$199:$A$202,0))/100 -> 0.063829787 | P13: U$S | Q13: =+R50 -> 316.69012 | S13: =+((Q13*J4)/1000)/J6 -> 9.2717651 | T13: xKg
B15: Detalle | E15: Mic | F15: Valor x Kgrs (U$S) | H15: Mtrs a trabajar | J15: Kgrs a trabajar | K15: Kgrs x 1000 Mts | L15: Kgrs x 1000 Mts | M15: Valor x 1000 mts | O15: Valor Kgrs | Q15: Valor x Millar | S15: Incidencia
A16: 1 | B16: =+D4 -> PoliesterCristal | E16: =+F4 -> 12 | F16: =(IF(B16=Tabla!$A$16,Tabla!$D$16,IF(B16=Tabla!$A$17,Tabla!$D$17,IF(B16=Tabla!$A$18,Tabla!$D$18,IF(B16=Tabla!$A$19,Tabla!$D$19,IF(B16=Tabla!$A$20,Tabla!$D$20,IF(B16=Tabla!$A$21,Tabla!$D$21,IF(B16=Tabla!$A$22,Tabla!$D$22,IF(B16=Tabla!$A$23,Tabla!$D$23,IF(B16=Tabla!$A$24,Tabla!$D$24,IF(B16=Tabla!$A$25,Tabla!$D$25,IF(B16=Tabla!$A$26,Tabla!$D$26,IF(B16=Tabla!$A$27,Tabla!$D$27,IF(B16=Tabla!$A$28,Tabla!$D$28,IF(B16=Tabla!$A$29,Tabla!$D$29,IF(B16=Tabla!$A$30,Tabla!$D$30,IF(B16=Tabla!$A$31,Tabla!$D$31,IF(B16=Tabla!$A$32,Tabla!$D$32,IF(B16=Tabla!$A$33,Tabla!$D$33)))))))))))))))))))*A16 -> 3.65 | H16: =+J5+(1500*(R8+R9)) -> 14000 | J16: =(IF(B16=Tabla!$A$16,Tabla!$C$16,IF(B16=Tabla!$A$17,Tabla!$C$17,IF(B16=Tabla!$A$18,Tabla!$C$18,IF(B16=Tabla!$A$19,Tabla!$C$19,IF(B16=Tabla!$A$20,Tabla!$C$20,IF(B16=Tabla!$A$21,Tabla!$C$21,IF(B16=Tabla!$A$22,Tabla!$C$22,IF(B16=Tabla!$A$23,Tabla!$C$23,IF(B16=Tabla!$A$24,Tabla!$C$24,IF(B16=Tabla!$A$25,Tabla!$C$25,IF(B16=Tabla!$A$26,Tabla!$C$26,IF(B16=Tabla!$A$27,Tabla!$C$27,IF(B16=Tabla!$A$28,Tabla!$C$28,IF(B16=Tabla!$A$29,Tabla!$C$29,IF(B16=Tabla!$A$30,Tabla!$C$30,IF(B16=Tabla!$A$31,Tabla!$C$31,IF(B16=Tabla!$A$32,Tabla!$C$32,IF(B16=Tabla!$A$33,Tabla!$C$33,””)))))))))))))))))))*(H16/1000)*((D10+J8)/100)*E16 -> 168.1848 | K16: =(IF(B16=Tabla!$A$16,Tabla!$C$16,IF(B16=Tabla!$A$17,Tabla!$C$17,IF(B16=Tabla!$A$18,Tabla!$C$18,IF(B16=Tabla!$A$19,Tabla!$C$19,IF(B16=Tabla!$A$20,Tabla!$C$20,IF(B16=Tabla!$A$21,Tabla!$C$21,IF(B16=Tabla!$A$22,Tabla!$C$22,IF(B16=Tabla!$A$23,Tabla!$C$23,IF(B16=Tabla!$A$24,Tabla!$C$24,IF(B16=Tabla!$A$25,Tabla!$C$25,IF(B16=Tabla!$A$26,Tabla!$C$26,IF(B16=Tabla!$A$27,Tabla!$C$27,IF(B16=Tabla!$A$28,Tabla!$C$28,IF(B16=Tabla!$A$29,Tabla!$C$29,IF(B16=Tabla!$A$30,Tabla!$C$30,IF(B16=Tabla!$A$31,Tabla!$C$31,IF(B16=Tabla!$A$32,Tabla!$C$32,IF(B16=Tabla!$A$33,Tabla!$C$33,””)))))))))))))))))))*E16*((D10+J8)/100) -> 12.0132 | L16: =(IF(B16=Tabla!$A$16,Tabla!$C$16,IF(B16=Tabla!$A$17,Tabla!$C$17,IF(B16=Tabla!$A$18,Tabla!$C$18,IF(B16=Tabla!$A$19,Tabla!$C$19,IF(B16=Tabla!$A$20,Tabla!$C$20,IF(B16=Tabla!$A$21,Tabla!$C$21,IF(B16=Tabla!$A$22,Tabla!$C$22,IF(B16=Tabla!$A$23,Tabla!$C$23,IF(B16=Tabla!$A$24,Tabla!$C$24,IF(B16=Tabla!$A$25,Tabla!$C$25,IF(B16=Tabla!$A$26,Tabla!$C$26,IF(B16=Tabla!$A$27,Tabla!$C$27,IF(B16=Tabla!$A$28,Tabla!$C$28,IF(B16=Tabla!$A$29,Tabla!$C$29,IF(B16=Tabla!$A$30,Tabla!$C$30,IF(B16=Tabla!$A$31,Tabla!$C$31,IF(B16=Tabla!$A$32,Tabla!$C$32,IF(B16=Tabla!$A$33,Tabla!$C$33,””)))))))))))))))))))*E16*(D9/100) -> 11.5056 | M16: U$S | N16: =((J16*F16)/(J5/1000)) -> 49.109962 | O16: U$S | P16: =N16/(SUM(L16:L18)) -> 0.35944919 | Q16: U$S | R16: =IF(R6>1,((+N16/(100/D3))/R6),+N16/(100/D3)) -> 12.27749 | S16: =(R16*100)/(Q12-R43-R44) -> 6.4369518 | T16: %
A17: 1 | B17: =+D5 -> PolietilenoDpk | E17: =+F5 -> 200 | F17: =(IF(B17=Tabla!$A$16,Tabla!$D$16,IF(B17=Tabla!$A$17,Tabla!$D$17,IF(B17=Tabla!$A$18,Tabla!$D$18,IF(B17=Tabla!$A$19,Tabla!$D$19,IF(B17=Tabla!$A$20,Tabla!$D$20,IF(B17=Tabla!$A$21,Tabla!$D$21,IF(B17=Tabla!$A$22,Tabla!$D$22,IF(B17=Tabla!$A$23,Tabla!$D$23,IF(B17=Tabla!$A$24,Tabla!$D$24,IF(B17=Tabla!$A$25,Tabla!$D$25,IF(B17=Tabla!$A$26,Tabla!$D$26,IF(B17=Tabla!$A$27,Tabla!$D$27,IF(B17=Tabla!$A$28,Tabla!$D$28,IF(B17=Tabla!$A$29,Tabla!$D$29,IF(B17=Tabla!$A$30,Tabla!$D$30,IF(B17=Tabla!$A$31,Tabla!$D$31,IF(B17=Tabla!$A$32,Tabla!$D$32,IF(B17=Tabla!$A$33,Tabla!$D$33)))))))))))))))))))*A17 -> 3.3235674 | H17: =+J5+100 -> 12600 | J17: =(IF(B17=Tabla!$A$16,Tabla!$C$16,IF(B17=Tabla!$A$17,Tabla!$C$17,IF(B17=Tabla!$A$18,Tabla!$C$18,IF(B17=Tabla!$A$19,Tabla!$C$19,IF(B17=Tabla!$A$20,Tabla!$C$20,IF(B17=Tabla!$A$21,Tabla!$C$21,IF(B17=Tabla!$A$22,Tabla!$C$22,IF(B17=Tabla!$A$23,Tabla!$C$23,IF(B17=Tabla!$A$24,Tabla!$C$24,IF(B17=Tabla!$A$25,Tabla!$C$25,IF(B17=Tabla!$A$26,Tabla!$C$26,IF(B17=Tabla!$A$27,Tabla!$C$27,IF(B17=Tabla!$A$28,Tabla!$C$28,IF(B17=Tabla!$A$29,Tabla!$C$29,IF(B17=Tabla!$A$30,Tabla!$C$30,IF(B17=Tabla!$A$31,Tabla!$C$31,IF(B17=Tabla!$A$32,Tabla!$C$32,IF(B17=Tabla!$A$33,Tabla!$C$33,””)))))))))))))))))))*(H17/1000)*((D10+J9)/100)*E17 -> 1646.064 | K17: =(IF(B17=Tabla!$A$16,Tabla!$C$16,IF(B17=Tabla!$A$17,Tabla!$C$17,IF(B17=Tabla!$A$18,Tabla!$C$18,IF(B17=Tabla!$A$19,Tabla!$C$19,IF(B17=Tabla!$A$20,Tabla!$C$20,IF(B17=Tabla!$A$21,Tabla!$C$21,IF(B17=Tabla!$A$22,Tabla!$C$22,IF(B17=Tabla!$A$23,Tabla!$C$23,IF(B17=Tabla!$A$24,Tabla!$C$24,IF(B17=Tabla!$A$25,Tabla!$C$25,IF(B17=Tabla!$A$26,Tabla!$C$26,IF(B17=Tabla!$A$27,Tabla!$C$27,IF(B17=Tabla!$A$28,Tabla!$C$28,IF(B17=Tabla!$A$29,Tabla!$C$29,IF(B17=Tabla!$A$30,Tabla!$C$30,IF(B17=Tabla!$A$31,Tabla!$C$31,IF(B17=Tabla!$A$32,Tabla!$C$32,IF(B17=Tabla!$A$33,Tabla!$C$33,””)))))))))))))))))))*E17*((D10+J8)/100) -> 130.64 | L17: =(IF(B17=Tabla!$A$16,Tabla!$C$16,IF(B17=Tabla!$A$17,Tabla!$C$17,IF(B17=Tabla!$A$18,Tabla!$C$18,IF(B17=Tabla!$A$19,Tabla!$C$19,IF(B17=Tabla!$A$20,Tabla!$C$20,IF(B17=Tabla!$A$21,Tabla!$C$21,IF(B17=Tabla!$A$22,Tabla!$C$22,IF(B17=Tabla!$A$23,Tabla!$C$23,IF(B17=Tabla!$A$24,Tabla!$C$24,IF(B17=Tabla!$A$25,Tabla!$C$25,IF(B17=Tabla!$A$26,Tabla!$C$26,IF(B17=Tabla!$A$27,Tabla!$C$27,IF(B17=Tabla!$A$28,Tabla!$C$28,IF(B17=Tabla!$A$29,Tabla!$C$29,IF(B17=Tabla!$A$30,Tabla!$C$30,IF(B17=Tabla!$A$31,Tabla!$C$31,IF(B17=Tabla!$A$32,Tabla!$C$32,IF(B17=Tabla!$A$33,Tabla!$C$33,””)))))))))))))))))))*E17*(D9/100) -> 125.12 | M17: U$S | N17: =((J17*F17)/(J5/1000)) -> 437.66437 | O17: U$S | P17: =N17/(SUM(L16:L18)) -> 3.2033848 | Q17: U$S | R17: =IF(R6>1,((+N17/(100/D3))/R6),+N17/(100/D3)) -> 109.41609 | S17: =(R17*100)/(Q12-R43-R44) -> 57.365641 | T17: %
A18: 1 | B18: =+D6 -> Otro | E18: =+F6 -> 0 | F18: =(IF(B18=Tabla!$A$16,Tabla!$D$16,IF(B18=Tabla!$A$17,Tabla!$D$17,IF(B18=Tabla!$A$18,Tabla!$D$18,IF(B18=Tabla!$A$19,Tabla!$D$19,IF(B18=Tabla!$A$20,Tabla!$D$20,IF(B18=Tabla!$A$21,Tabla!$D$21,IF(B18=Tabla!$A$22,Tabla!$D$22,IF(B18=Tabla!$A$23,Tabla!$D$23,IF(B18=Tabla!$A$24,Tabla!$D$24,IF(B18=Tabla!$A$25,Tabla!$D$25,IF(B18=Tabla!$A$26,Tabla!$D$26,IF(B18=Tabla!$A$27,Tabla!$D$27,IF(B18=Tabla!$A$28,Tabla!$D$28,IF(B18=Tabla!$A$29,Tabla!$D$29,IF(B18=Tabla!$A$30,Tabla!$D$30,IF(B18=Tabla!$A$31,Tabla!$D$31,IF(B18=Tabla!$A$32,Tabla!$D$32,IF(B18=Tabla!$A$33,Tabla!$D$33)))))))))))))))))))*A18 -> 0 | H18: =+J5+100 -> 12600 | J18: =(IF(B18=Tabla!$A$16,Tabla!$C$16,IF(B18=Tabla!$A$17,Tabla!$C$17,IF(B18=Tabla!$A$18,Tabla!$C$18,IF(B18=Tabla!$A$19,Tabla!$C$19,IF(B18=Tabla!$A$20,Tabla!$C$20,IF(B18=Tabla!$A$21,Tabla!$C$21,IF(B18=Tabla!$A$22,Tabla!$C$22,IF(B18=Tabla!$A$23,Tabla!$C$23,IF(B18=Tabla!$A$24,Tabla!$C$24,IF(B18=Tabla!$A$25,Tabla!$C$25,IF(B18=Tabla!$A$26,Tabla!$C$26,IF(B18=Tabla!$A$27,Tabla!$C$27,IF(B18=Tabla!$A$28,Tabla!$C$28,IF(B18=Tabla!$A$29,Tabla!$C$29,IF(B18=Tabla!$A$30,Tabla!$C$30,IF(B18=Tabla!$A$31,Tabla!$C$31,IF(B18=Tabla!$A$32,Tabla!$C$32,IF(B18=Tabla!$A$33,Tabla!$C$33,””)))))))))))))))))))*(H18/1000)*((D10+J10)/100)*E18 -> 0 | K18: =(IF(B18=Tabla!$A$16,Tabla!$C$16,IF(B18=Tabla!$A$17,Tabla!$C$17,IF(B18=Tabla!$A$18,Tabla!$C$18,IF(B18=Tabla!$A$19,Tabla!$C$19,IF(B18=Tabla!$A$20,Tabla!$C$20,IF(B18=Tabla!$A$21,Tabla!$C$21,IF(B18=Tabla!$A$22,Tabla!$C$22,IF(B18=Tabla!$A$23,Tabla!$C$23,IF(B18=Tabla!$A$24,Tabla!$C$24,IF(B18=Tabla!$A$25,Tabla!$C$25,IF(B18=Tabla!$A$26,Tabla!$C$26,IF(B18=Tabla!$A$27,Tabla!$C$27,IF(B18=Tabla!$A$28,Tabla!$C$28,IF(B18=Tabla!$A$29,Tabla!$C$29,IF(B18=Tabla!$A$30,Tabla!$C$30,IF(B18=Tabla!$A$31,Tabla!$C$31,IF(B18=Tabla!$A$32,Tabla!$C$32,IF(B18=Tabla!$A$33,Tabla!$C$33,””)))))))))))))))))))*E18*((D10+J8)/100) -> 0 | L18: =(IF(B18=Tabla!$A$16,Tabla!$C$16,IF(B18=Tabla!$A$17,Tabla!$C$17,IF(B18=Tabla!$A$18,Tabla!$C$18,IF(B18=Tabla!$A$19,Tabla!$C$19,IF(B18=Tabla!$A$20,Tabla!$C$20,IF(B18=Tabla!$A$21,Tabla!$C$21,IF(B18=Tabla!$A$22,Tabla!$C$22,IF(B18=Tabla!$A$23,Tabla!$C$23,IF(B18=Tabla!$A$24,Tabla!$C$24,IF(B18=Tabla!$A$25,Tabla!$C$25,IF(B18=Tabla!$A$26,Tabla!$C$26,IF(B18=Tabla!$A$27,Tabla!$C$27,IF(B18=Tabla!$A$28,Tabla!$C$28,IF(B18=Tabla!$A$29,Tabla!$C$29,IF(B18=Tabla!$A$30,Tabla!$C$30,IF(B18=Tabla!$A$31,Tabla!$C$31,IF(B18=Tabla!$A$32,Tabla!$C$32,IF(B18=Tabla!$A$33,Tabla!$C$33,””)))))))))))))))))))*E18*(D9/100) -> 0 | M18: U$S | N18: =((J18*F18)/(J5/1000)) -> 0 | O18: U$S | P18: =N18/(SUM(L16:L18)) -> 0 | Q18: U$S | R18: =IF(R6>1,((+N18/(100/D3))/R6),+N18/(100/D3)) -> 0 | S18: =(R18*100)/(Q12-R43-R44) -> 0 | T18: %
A19: =IF(D7="SI",1,0) -> 1 | B19: Costo Impresora | E19: Prep | F19: Prod | G19: Prep | H19: SobreImpresion | J19: Valor Hs
A20: =IF(F7="SI",1,0) -> 0 | B20: Reprint | E20: =(Tabla!$D$5*R8+1*R9)*A19 -> 1.5 | F20: =(+J5/20000)*A19 -> 0.625 | G20: =(Tabla!$D$5/3)*A20 -> 0 | H20: =(J5/20000)*A20 -> 0 | J20: U$S | K20: =+Tabla!$B$5 -> 58.46 | M20: U$S | N20: =((E20+F20+G20+H20)*K20)/(J5/1000)*A19 -> 9.9382 | O20: U$S | P20: =N20/(SUM(L16:L18)) -> 0.072740394 | Q20: U$S | R20: =IF(R6>1,((+N20/(100/D3))/R6),+N20/(100/D3)) -> 2.48455 | S20: =(R20*100)/(Q12-R43-R44) -> 1.302622 | T20: %
A21: =IF(D7="SI",1,0) -> 1 | B21: Tela Doble Fax | I21: =(+L21/S10)*A20 -> 0 | J21: x Color U$S | L21: =(IF(B21=Tabla!$A$79,((Tabla!$B$79/2300/46)*(D10+J8)*N9),1)*0.75) -> 10.040997 | O21: U$S | P21: =((I21+L21*S10)/J6)*A21 -> 0.047035389 | Q21: U$S | R21: =IF(R6>1,((((I21+L21*R10)/(J4/1000)*A21))/R6),((I21+L21*R10)/(J4/1000)*A21)) -> 1.6065595 | S21: =(R21*100)/(Q12-R43-R44) -> 0.84230132 | T21: %
A22: =IF(D7="SI",1,0) -> 1 | B22: Tintas + Diluyentes | I22: =(((Tabla!$B$90*0.8)+(Tabla!$B$93*0.2))/1000*2)*A20 -> 0 | J22: Valor grs/mts2 | L22: =(((((Tabla!$J$116-Tabla!$E$116)/1000*2)+((Tabla!$E$116/1000*2)*S9)/100)*R11)/100)+I22 -> 0.030711123 | M22: U$S | N22: =(L22*((D10+J8)*10)*A22)*(R10/8) -> 21.804897 | O22: U$S | P22: =N22/(SUM(L16:L18)) -> 0.15959599 | Q22: U$S | R22: =IF(R6>1,((+N22/(100/D3))/R6),+N22/(100/D3)) -> 5.4512244 | S22: =(R22*100)/(Q12-R43-R44) -> 2.8580164 | T22: %
A23: =IF(D7="SI",1,0) -> 1 | B23: Limpieza Diluyentes | E23: =IF(J5>240000,120,IF(J5>210000,96,IF(J5>180000,72,IF(J5>150000,64,IF(J5>120000,48,IF(J5>60000,24,IF(J5>30000,16,12))))))) -> 12 | J23: Valor Lts | L23: =+Tabla!$B$99 -> 1.25 | M23: U$S | N23: =(+L23*E23/J5*1000)*A23 -> 1.2 | O23: U$S | P23: =N23/(SUM(L16:L18)) -> 0.008783127 | Q23: U$S | R23: =IF(R6>1,((+N23/(100/D3))/R6),+N23/(100/D3)) -> 0.3 | S23: =(R23*100)/(Q12-R43-R44) -> 0.15728667 | T23: %
A24: =IF(J7="SI",1,IF(J7="BI",2,0)) -> 1 | B24: Costo Laminado | E24: =+Tabla!$D$6*(A24+A26) -> 0.5 | F24: =+J5/Tabla!$C$6*(A25+A26) -> 0.78125 | J24: U$S | K24: =+Tabla!$B$6 -> 41.35 | M24: U$S | N24: =((E24+F24)*K24)/(J5/1000) -> 4.238375 | O24: U$S | P24: =N24/(SUM(L16:L18)) -> 0.031021822 | Q24: U$S | R24: =IF(R6>1,((+N24/(100/D3))/R6),+N24/(100/D3)) -> 1.0595937 | S24: =(R24*100)/(Q12-R43-R44) -> 0.55553323 | T24: %
A25: =IF(J7="SI",1,IF(J7="BI",2,0)) -> 1 | B25: Solvent Less | J25: Valor grs/mts2 | L25: =IF(J7="SI",+(((Tabla!$B$123/1000*Tabla!$C$123)+(Tabla!$B$124/1000*Tabla!C350))*Tabla!$B$122)*A25,IF(J7="BI",+(((Tabla!$B$123/1000*Tabla!$C$123)+(Tabla!$B$124/1000*Tabla!C350))*Tabla!$B$122)*A25,0)) -> 0.012474 | M25: U$S | N25: =L25*((D10+J9+J10)*10) -> 8.85654 | O25: U$S | P25: =N25/(SUM(L16:L18)) -> 0.06482343 | Q25: U$S | R25: =IF(R6>1,((+N25/(100/D3))/R6),+N25/(100/D3)) -> 2.214135 | S25: =(R25*100)/(Q12-R43-R44) -> 1.1608464 | T25: %
A26: =IF(N7="SI",1,IF(N7="BI",2,0)) -> 0 | B26: Solvent | J26: Valor grs/mts2 | L26: =IF(N7="SI",+((Tabla!$B$127/1000)*Tabla!$B$126)*A26,IF(N7="BI",+((Tabla!$B$127/1000)*Tabla!$B$126)*A26,0)) -> 0 | M26: U$S | N26: =L26*(D10*10) -> 0 | O26: U$S | P26: =N26/(SUM(L16:L18)) -> 0 | Q26: U$S | R26: =IF(R6>1,((+N26/(100/D3))/R6),+N26/(100/D3)) -> 0 | S26: =(R26*100)/(Q12-R43-R44) -> 0 | T26: %
B27: Refilado | E27: =+Tabla!$D$7 -> 0 | F27: =+J5/Tabla!$C$7 -> 1.5625 | J27: U$S | K27: =+Tabla!$B$7 -> 39.54 | M27: U$S | N27: =((E27+F27)*K27)/(J5/1000) -> 4.9425 | O27: U$S | P27: =N27/(SUM(L16:L18)) -> 0.036175504 | Q27: U$S | R27: =IF(R6>1,((+N27/(100/D3))/R6),+N27/(100/D3)) -> 1.235625 | S27: =(R27*100)/(Q12-R43-R44) -> 0.64782446 | T27: %
A28: =+Tabla!$E$7 -> 0.05 | B28: % Material Scrap | M28: U$S | N28: =((SUM(P16:P27))*A28) -> 0.19915048 | O28: U$S | P28: =((SUM(P16:P27))*A28) -> 0.19915048 | Q28: U$S | R28: =+N28/(100/D3) -> 0.04978762 | S28: =(R28*100)/(Q12-R43-R44) -> 0.026103096 | T28: %
B29: Costo Bobina | O29: U$S | P29: =SUM(P16:P28) -> 4.1821601
A30: =IF(D3>=38,Tabla!$E$155,IF(D3>=25,Tabla!$E$150,IF(D3>=18,Tabla!$E$147,IF(D3>=15,Tabla!$E$144,Tabla!$E$139))))-(A31*Tabla!$G$139) -> 40 | B30: Costo Confeccionadora | E30: 1 | F30: =+J4/+(A30*60) -> 20.833333 | J30: U$S | K30: =+Tabla!$B$8 -> 60.01 | L30: =+(((+E30+F30)*K30)/J4)*1000 -> 26.204367 | M30: U$S | N30: =((E30+F30)*K30)/(J5/1000) -> 104.81747 | O30: U$S | P30: =N30/(SUM(L16:L18)) -> 0.7671876 | Q30: U$S | R30: =+N30/(100/D3) -> 26.204367 | S30: =(R30*100)/(Q12-R43-R44) -> 13.738658 | T30: %
A31: =IF(S3="SI",1,0) -> 0 | B31: Zipper | E31: Scrap | F31: =+Tabla!$F$8 -> 100 | M31: U$S | N31: =+Tabla!$B$132*(1000+F31)*A31 -> 0 | O31: U$S | P31: =N31/(SUM(L16:L18)) -> 0 | Q31: U$S | R31: =+N31/(100/D3) -> 0 | S31: =(R31*100)/(Q12-R43-R44) -> 0 | T31: %
A32: =IF(S4="SI",1,0) -> 0 | B32: Troquel | E32: Scrap | F32: =+Tabla!$F$8 -> 100 | M32: U$S | N32: =+Tabla!$E$132*(1000+F32)*A32 -> 0 | O32: U$S | P32: =N32/(SUM(L16:L18)) -> 0 | Q32: U$S | R32: =+Tabla!$E$132*(1000+F32)*A32 -> 0 | S32: =(R32*100)/(Q12-R43-R44) -> 0 | T32: %
A33: =+Tabla!$E$8 -> 0.15 | B33: Scrap Confeccionadora | M33: U$S | N33: =+(P29*A33)/(100000/D3)*1000 -> 0.156831 | O33: U$S | P33: =N33/(SUM(L16:L18)) -> 0.0011478889 | Q33: U$S | R33: =SUM(R16:R31)*A33 -> 24.344914 | S33: =(R33*100)/(Q12-R43-R44) -> 12.763768 | T33: %
A34: =+Tabla!$C$10 -> 20 | B34: Costo Picotera | E34: =+Tabla!$D$10 -> 0.5 | F34: =+J4/+(A34*60) -> 41.666667 | J34: U$S | K34: =+Tabla!$B$10 -> 20.003333 | L34: =+(((+E34+F34)*K34)/J4)*1000 -> 16.869478 | M34: U$S | N34: =((E34+F34)*K34)/(J5/1000) -> 67.477911 | O34: U$S | P34: =N34/(SUM(L16:L18)) -> 0.49388922 | Q34: U$S | R34: =+N34/(100/D3)*A35 -> 0 | S34: =(R34*100)/(Q12-R43-R44) -> 0 | T34: %
A35: =IF(S5="SI",1,0) -> 0 | B35: Picos | E35: Scrap | F35: =+Tabla!$F$10 -> 100 | M35: U$S | N35: =+Tabla!$E$133*(1000+F35)*A35 -> 0 | O35: U$S | P35: =N35/(SUM(L16:L18)) -> 0 | Q35: U$S | R35: =+Tabla!$E$133*(1000+F35)*A35 -> 0 | S35: =(R35*100)/(Q12-R43-R44) -> 0 | T35: %
A36: =+Tabla!$E$10 -> 0.05 | B36: Scrap Picotera | M36: U$S | N36: =+(P29*A36)/(100000/D3)*1000 -> 0.052277001 | O36: U$S | P36: =N36/(SUM(L16:L18)) -> 0.00038262962 | Q36: U$S | R36: =SUM(R16:R35)*A36*A35 -> 0 | S36: =(R36*100)/(Q12-R43-R44) -> 0 | T36: %
A37: =IF(D3>22.1,400,IF(D3>=15,1000,IF(D3>=12,1500,2000))) -> 400 | B37: x Caja | M37: U$S | N37: =+Tabla!$B$133/A37*1000 -> 0.94110561 | O37: U$S | P37: =N37/(SUM(L16:L18)) -> 0.0068882084 | Q37: U$S | R37: =1000/A37*N37 -> 2.352764 | S37: =(R37*100)/(Q12-R43-R44) -> 1.233528 | T37: %
A38: =+T11 -> 1 | B38: Flete | D38: =+S12 -> Caba | E38: =+T12 -> 900 | F38: =INDEX(Tabla!$B$162:$E$187,MATCH(S12,Tabla!$A$162:$A$187,0),MATCH(T12,Tabla!$B$161:$E$161,0))*A38 -> 57.182178 | O38: U$S | P38: =F38/(SUM(J6)) -> 0.033482556 | Q38: U$S | R38: =+J6*P38/J4*1000 -> 1.1436436 | S38: =(R38*100)/(Q12-R43-R44) -> 0.59959961 | T38: %
A39: =IF(J11="SI",1,0) -> 0 | B39: Extras | O39: U$S | P39: =(+L11/J6)*A39 -> 0 | Q39: U$S | R39: =(+L11/J4)*A39 -> 0 | S39: =(R39*100)/(Q12-R43-R44) -> 0 | T39: %
B40: Costo Envase | O40: U$S | P40: =SUM(P30:P39) -> 1.3029781 | S40: =(SUM(R20,R24,R27,R30)+SUM(A42:A44)+E43)/100 -> 0.66984135 | T40: Costo Produc
A41: Rentabilidad | K41: Financiado | L41: Costo Bruto | O41: U$S | P41: =+P40+P29 -> 5.4851382 | Q41: U$S | R41: =SUM(R16:R39)+(R45*A45) -> 190.14075 | S41: Costo Financiación Bancaria
A42: 34 | B42: % Plus | C42: Cliente | E42: =+K1 -> A | F42: U$S | G42: =+I42*J6 -> 5050.6136 | I42: =+((((R42*J4)/1000)/J6)) -> 2.9573454 | J42: xKg | K42: =+((((T44*J4)/1000)/J6)) -> 2.3836549 | L42: Rentabilidad Bobina | O42: U$S | P42: =(P46*(A42/100)) -> 2.9139797 | Q42: U$S | R42: =(R46*(A42/100)) -> 101.01227 | S42: U$S | T42: =+R50-R48 -> 19.595201
A43: =IF(K1="A",Tabla!$J$217,IF(K1="B",Tabla!$K$217,IF(K1="C",Tabla!$L$217,Tabla!$M$217))) -> 0 | B43: % | C43: Ajuste | E43: =+N1 -> 0 | F43: U$S | G43: =+I43*J6 -> 5050.6136 | I43: =+((((R43*J4)/1000)/J6)) -> 2.9573454 | J43: xKg | K43: =K42*J6 -> 4070.8535 | L43: Confección | O43: U$S | P43: =+P48-P41-P44 -> 2.9139797 | Q43: U$S | R43: =+R48-R41-R44 -> 101.01227 | S43: Rentabilidad Bonificando
A44: =IF(S1="AK",Tabla!$B$191,IF(S1="PM",Tabla!$B$192,IF(S1="4P",Tabla!$B$193,Tabla!$B$194)))+T2 -> 2 | B44: % Comision | E44: =+S1 -> AK | F44: U$S | G44: =+I44*J6 -> 297.09492 | I44: =+(((R44*J4)/1000)/J6) -> 0.17396149 | J44: xKg | K44: Bonificación | L44: U$S | M44: =+I43-P43 -> 0.043365684 | O44: U$S | P44: =+P46*(A44/100) -> 0.17141057 | Q44: U$S | R44: =+R48*(A44/100) -> 5.9418983 | S44: U$S | T44: =+R43-T42 -> 81.41707
A45: 0 | B45: Costo Polímeros | E45: 1 | F45: U$S | G45: =+(D10*(N9+3)*S10*0.055) -> 1655.72 | I45: =+G45/J6 -> 0.96949327 | J45: xKg | K45: =+G43-K43 -> 979.76005 | O45: U$S | P45: =+I45*A45 -> 0 | Q45: U$S | R45: =(+J6*I45/J4*1000)*A45 -> 0
B46: Rentabilidad Bonificando Polímeros | F46: U$S | G46: =+I46*J6 -> 5050.6136 | I46: =I43-(I45*E45*A45) -> 2.9573454 | J46: xKg | O46: U$S | P46: =+P41/(1-((A42+A44)/100)) -> 8.5705285 | Q46: U$S | R46: =+R41/(1-((A42+A44)/100)) -> 297.09492
O47: U$S | P47: =+P46*(E43/100) -> 0 | Q47: U$S | R47: =+R46*(E43/100) -> 0
F48: Valor por Millar al contado | O48: U$S | P48: =+P46+P47 -> 8.5705285 | Q48: U$S | R48: =+R46+R47 -> 297.09492
Q49: U$S | R49: =(+R41/(1-((A42+(A44+(A44*N13)))/100)))+R46*(E43/100) -> 297.68871
F50: Valor por Kgrs a | J50: =+K13 -> 45 | K50: días FF | M50: =+N13 -> 0.063829787 | O50: U$S | P50: =+(P48*M50)+P48 -> 9.1175835 | Q50: U$S | R50: =+(R49*M50)+R49 -> 316.69012

Sheet Confeccion 4Costuras
A1: 4PACK | C1: Cliente | K1: A | L1: Ajuste | N1: 0 | Q1: Vendedor | S1: AK
A2: DOYPACK | C2: 4 Costuras | K2: Nro. de Cotizacion: | M2: 0409 | O2: / 2026 | Q2: =TODAY() -> 46286 | S2: Ajuste | T2: 0
B3: Ancho | D3: 24 | F3: cm | G3: Alto | J3: 54 | K3: cm | L3: Fuelle Total | N3: 14 | O3: cm | Q3: ZIPPER | S3: NO
A4: Proveedor | B4: Vitopel | D4: PolietilenoCristal | F4: 40 | G4: mic | H4: Envases | J4: 80000 | K4: unidades | R4: TROQUEL | S4: NO
B5: Ingepol | D5: PolietilenoDpk | F5: 90 | G5: mic | H5: Cantidad | J5: =(+J4*D3/100)/R6 -> 19200 | K5: mts | R5: PICO | S5: NO
B6: Otro | D6: Otro | F6: 0 | G6: mic | H6: Peso | J6: =(SUM(L16:L18))*(J5/1000) -> 1423.7184 | K6: Kgrs | P6: Modulos en el Ancho | R6: 1 | S6: Calle Interna entre Modulos
B7: IMPRESIÓN | D7: SI | E7: RePRINT | F7: NO | G7: LAMINACION SIN SOLVENTE | J7: SI | K7: CON SOLVENTE | N7: NO | O7: =+N8*R7 -> 54 | P7: Modulos Desarrollo | R7: 1 | S7: 0
B8: Ancho | D8: =+(D3*2)+N3 -> 62 | F8: cm | G8: Impresión Scrap | J8: 0 | K8: cm | L8: Paso | N8: =+J3 -> 54 | O8: cm | P8: Diseños | R8: 1 | S8: Blanco %
B9: Ancho Refilado | D9: =(+D8*R6)+S7 -> 62 | F9: cm | G9: Laminación Scrap | J9: 0 | K9: cm | L9: Desarrollo | N9: =IF(O7=Tabla!$L$87,Tabla!$L$87,IF(O7=Tabla!$L$88,Tabla!$L$88,IF(O7=Tabla!$L$89,Tabla!$L$89,IF(O7=Tabla!$L$90,Tabla!$L$90,IF(O7=Tabla!$L$91,Tabla!$L$91,IF(O7=Tabla!$L$92,Tabla!$L$92,IF(O7=Tabla!$L$93,Tabla!$L$93,IF(O7=Tabla!$L$94,Tabla!$L$94,IF(O7=Tabla!$L$95,Tabla!$L$95,IF(O7=Tabla!$L$96,Tabla!$L$96,IF(O7=Tabla!$L$97,Tabla!$L$97,IF(O7=Tabla!$L$98,Tabla!$L$98,IF(O7=Tabla!$L$99,Tabla!$L$99,IF(O7=Tabla!$L$100,Tabla!$L$100,IF(O7=Tabla!$L$101,Tabla!$L$101,IF(O7=Tabla!$L$102,Tabla!$L$102,IF(O7=Tabla!$L$103,Tabla!$L$103,IF(O7=Tabla!$L$104,Tabla!$L$104,IF(O7=Tabla!$L$105,Tabla!$L$105,IF(O7=Tabla!$L$106,Tabla!$L$106,”NO DISPBLE”)))))))))))))))))))) -> 54 | O9: cm | P9: Cambios | R9: 0 | S9: 100
B10: Ancho Lamina | D10: =+D9+3 -> 65 | F10: cm | G10: Bilaminación Scrap | J10: 0 | K10: cm | L10: Mangas Disp | N10: 45 | O10: cm | P10: Colores | R10: 7 | S10: =+R10*(R8+R9) -> 7
G11: Extras | J11: NO | K11: U$S | L11: 0 | P11: % Impreso | R11: 100 | S11: Flete | T11: 2
G12: 0 | P12: U$S | Q12: =+R49 -> 213.22693 | S12: Caba | T12: 900
G13: Valor por Kgrs a | K13: 30 | L13: días FF | N13: =INDEX(Tabla!$B$199:$B$202,MATCH(K13,Tabla!$A$199:$A$202,0))/100 -> 0.041666667 | P13: U$S | Q13: =+R50 -> 222.11139 | S13: =+((Q13*J4)/1000)/J6 -> 12.480636 | T13: xKg
B15: Detalle | E15: Mic | F15: Valor x Kgrs (U$S) | H15: Mtrs a trabajar | J15: Kgrs a trabajar | K15: Kgrs x 1000 Mts | L15: Kgrs x 1000 Mts | M15: Valor x 1000 mts | O15: Valor Kgrs | Q15: Valor x Millar | S15: Incidencia
A16: 1 | B16: =+D4 -> PolietilenoCristal | E16: =+F4 -> 40 | F16: =(IF(B16=Tabla!$A$16,Tabla!$D$16,IF(B16=Tabla!$A$17,Tabla!$D$17,IF(B16=Tabla!$A$18,Tabla!$D$18,IF(B16=Tabla!$A$19,Tabla!$D$19,IF(B16=Tabla!$A$20,Tabla!$D$20,IF(B16=Tabla!$A$21,Tabla!$D$21,IF(B16=Tabla!$A$22,Tabla!$D$22,IF(B16=Tabla!$A$23,Tabla!$D$23,IF(B16=Tabla!$A$24,Tabla!$D$24,IF(B16=Tabla!$A$25,Tabla!$D$25,IF(B16=Tabla!$A$26,Tabla!$D$26,IF(B16=Tabla!$A$27,Tabla!$D$27,IF(B16=Tabla!$A$28,Tabla!$D$28,IF(B16=Tabla!$A$29,Tabla!$D$29,IF(B16=Tabla!$A$30,Tabla!$D$30,IF(B16=Tabla!$A$31,Tabla!$D$31,IF(B16=Tabla!$A$32,Tabla!$D$32,IF(B16=Tabla!$A$33,Tabla!$D$33)))))))))))))))))))*A16 -> 3.1435674 | H16: =+J5+(1500*(R8+R9)) -> 20700 | J16: =(IF(B16=Tabla!$A$16,Tabla!$C$16,IF(B16=Tabla!$A$17,Tabla!$C$17,IF(B16=Tabla!$A$18,Tabla!$C$18,IF(B16=Tabla!$A$19,Tabla!$C$19,IF(B16=Tabla!$A$20,Tabla!$C$20,IF(B16=Tabla!$A$21,Tabla!$C$21,IF(B16=Tabla!$A$22,Tabla!$C$22,IF(B16=Tabla!$A$23,Tabla!$C$23,IF(B16=Tabla!$A$24,Tabla!$C$24,IF(B16=Tabla!$A$25,Tabla!$C$25,IF(B16=Tabla!$A$26,Tabla!$C$26,IF(B16=Tabla!$A$27,Tabla!$C$27,IF(B16=Tabla!$A$28,Tabla!$C$28,IF(B16=Tabla!$A$29,Tabla!$C$29,IF(B16=Tabla!$A$30,Tabla!$C$30,IF(B16=Tabla!$A$31,Tabla!$C$31,IF(B16=Tabla!$A$32,Tabla!$C$32,IF(B16=Tabla!$A$33,Tabla!$C$33,””)))))))))))))))))))*(H16/1000)*((D10+J8)/100)*E16 -> 495.144 | K16: =(IF(B16=Tabla!$A$16,Tabla!$C$16,IF(B16=Tabla!$A$17,Tabla!$C$17,IF(B16=Tabla!$A$18,Tabla!$C$18,IF(B16=Tabla!$A$19,Tabla!$C$19,IF(B16=Tabla!$A$20,Tabla!$C$20,IF(B16=Tabla!$A$21,Tabla!$C$21,IF(B16=Tabla!$A$22,Tabla!$C$22,IF(B16=Tabla!$A$23,Tabla!$C$23,IF(B16=Tabla!$A$24,Tabla!$C$24,IF(B16=Tabla!$A$25,Tabla!$C$25,IF(B16=Tabla!$A$26,Tabla!$C$26,IF(B16=Tabla!$A$27,Tabla!$C$27,IF(B16=Tabla!$A$28,Tabla!$C$28,IF(B16=Tabla!$A$29,Tabla!$C$29,IF(B16=Tabla!$A$30,Tabla!$C$30,IF(B16=Tabla!$A$31,Tabla!$C$31,IF(B16=Tabla!$A$32,Tabla!$C$32,IF(B16=Tabla!$A$33,Tabla!$C$33,””)))))))))))))))))))*E16*((D10+J8)/100) -> 23.92 | L16: =(IF(B16=Tabla!$A$16,Tabla!$C$16,IF(B16=Tabla!$A$17,Tabla!$C$17,IF(B16=Tabla!$A$18,Tabla!$C$18,IF(B16=Tabla!$A$19,Tabla!$C$19,IF(B16=Tabla!$A$20,Tabla!$C$20,IF(B16=Tabla!$A$21,Tabla!$C$21,IF(B16=Tabla!$A$22,Tabla!$C$22,IF(B16=Tabla!$A$23,Tabla!$C$23,IF(B16=Tabla!$A$24,Tabla!$C$24,IF(B16=Tabla!$A$25,Tabla!$C$25,IF(B16=Tabla!$A$26,Tabla!$C$26,IF(B16=Tabla!$A$27,Tabla!$C$27,IF(B16=Tabla!$A$28,Tabla!$C$28,IF(B16=Tabla!$A$29,Tabla!$C$29,IF(B16=Tabla!$A$30,Tabla!$C$30,IF(B16=Tabla!$A$31,Tabla!$C$31,IF(B16=Tabla!$A$32,Tabla!$C$32,IF(B16=Tabla!$A$33,Tabla!$C$33,””)))))))))))))))))))*E16*(D9/100) -> 22.816 | M16: U$S | N16: =((J16*F16)/(J5/1000)) -> 81.068673 | O16: U$S | P16: =N16/(SUM(L16:L18)) -> 1.093277 | Q16: U$S | R16: =IF(R6>1,((+N16/(100/D3))/R6),+N16/(100/D3)) -> 19.456482 | S16: =(R16*100)/(Q12-R43-R44) -> 15.193893 | T16: %
A17: 1 | B17: =+D5 -> PolietilenoDpk | E17: =+F5 -> 90 | F17: =(IF(B17=Tabla!$A$16,Tabla!$D$16,IF(B17=Tabla!$A$17,Tabla!$D$17,IF(B17=Tabla!$A$18,Tabla!$D$18,IF(B17=Tabla!$A$19,Tabla!$D$19,IF(B17=Tabla!$A$20,Tabla!$D$20,IF(B17=Tabla!$A$21,Tabla!$D$21,IF(B17=Tabla!$A$22,Tabla!$D$22,IF(B17=Tabla!$A$23,Tabla!$D$23,IF(B17=Tabla!$A$24,Tabla!$D$24,IF(B17=Tabla!$A$25,Tabla!$D$25,IF(B17=Tabla!$A$26,Tabla!$D$26,IF(B17=Tabla!$A$27,Tabla!$D$27,IF(B17=Tabla!$A$28,Tabla!$D$28,IF(B17=Tabla!$A$29,Tabla!$D$29,IF(B17=Tabla!$A$30,Tabla!$D$30,IF(B17=Tabla!$A$31,Tabla!$D$31,IF(B17=Tabla!$A$32,Tabla!$D$32,IF(B17=Tabla!$A$33,Tabla!$D$33)))))))))))))))))))*A17 -> 3.3235674 | H17: =+J5+100 -> 19300 | J17: =(IF(B17=Tabla!$A$16,Tabla!$C$16,IF(B17=Tabla!$A$17,Tabla!$C$17,IF(B17=Tabla!$A$18,Tabla!$C$18,IF(B17=Tabla!$A$19,Tabla!$C$19,IF(B17=Tabla!$A$20,Tabla!$C$20,IF(B17=Tabla!$A$21,Tabla!$C$21,IF(B17=Tabla!$A$22,Tabla!$C$22,IF(B17=Tabla!$A$23,Tabla!$C$23,IF(B17=Tabla!$A$24,Tabla!$C$24,IF(B17=Tabla!$A$25,Tabla!$C$25,IF(B17=Tabla!$A$26,Tabla!$C$26,IF(B17=Tabla!$A$27,Tabla!$C$27,IF(B17=Tabla!$A$28,Tabla!$C$28,IF(B17=Tabla!$A$29,Tabla!$C$29,IF(B17=Tabla!$A$30,Tabla!$C$30,IF(B17=Tabla!$A$31,Tabla!$C$31,IF(B17=Tabla!$A$32,Tabla!$C$32,IF(B17=Tabla!$A$33,Tabla!$C$33,””)))))))))))))))))))*(H17/1000)*((D10+J9)/100)*E17 -> 1038.726 | K17: =(IF(B17=Tabla!$A$16,Tabla!$C$16,IF(B17=Tabla!$A$17,Tabla!$C$17,IF(B17=Tabla!$A$18,Tabla!$C$18,IF(B17=Tabla!$A$19,Tabla!$C$19,IF(B17=Tabla!$A$20,Tabla!$C$20,IF(B17=Tabla!$A$21,Tabla!$C$21,IF(B17=Tabla!$A$22,Tabla!$C$22,IF(B17=Tabla!$A$23,Tabla!$C$23,IF(B17=Tabla!$A$24,Tabla!$C$24,IF(B17=Tabla!$A$25,Tabla!$C$25,IF(B17=Tabla!$A$26,Tabla!$C$26,IF(B17=Tabla!$A$27,Tabla!$C$27,IF(B17=Tabla!$A$28,Tabla!$C$28,IF(B17=Tabla!$A$29,Tabla!$C$29,IF(B17=Tabla!$A$30,Tabla!$C$30,IF(B17=Tabla!$A$31,Tabla!$C$31,IF(B17=Tabla!$A$32,Tabla!$C$32,IF(B17=Tabla!$A$33,Tabla!$C$33,””)))))))))))))))))))*E17*((D10+J8)/100) -> 53.82 | L17: =(IF(B17=Tabla!$A$16,Tabla!$C$16,IF(B17=Tabla!$A$17,Tabla!$C$17,IF(B17=Tabla!$A$18,Tabla!$C$18,IF(B17=Tabla!$A$19,Tabla!$C$19,IF(B17=Tabla!$A$20,Tabla!$C$20,IF(B17=Tabla!$A$21,Tabla!$C$21,IF(B17=Tabla!$A$22,Tabla!$C$22,IF(B17=Tabla!$A$23,Tabla!$C$23,IF(B17=Tabla!$A$24,Tabla!$C$24,IF(B17=Tabla!$A$25,Tabla!$C$25,IF(B17=Tabla!$A$26,Tabla!$C$26,IF(B17=Tabla!$A$27,Tabla!$C$27,IF(B17=Tabla!$A$28,Tabla!$C$28,IF(B17=Tabla!$A$29,Tabla!$C$29,IF(B17=Tabla!$A$30,Tabla!$C$30,IF(B17=Tabla!$A$31,Tabla!$C$31,IF(B17=Tabla!$A$32,Tabla!$C$32,IF(B17=Tabla!$A$33,Tabla!$C$33,””)))))))))))))))))))*E17*(D9/100) -> 51.336 | M17: U$S | N17: =((J17*F17)/(J5/1000)) -> 179.80603 | O17: U$S | P17: =N17/(SUM(L16:L18)) -> 2.4248305 | Q17: U$S | R17: =IF(R6>1,((+N17/(100/D3))/R6),+N17/(100/D3)) -> 43.153448 | S17: =(R17*100)/(Q12-R43-R44) -> 33.699252 | T17: %
A18: 1 | B18: =+D6 -> Otro | E18: =+F6 -> 0 | F18: =(IF(B18=Tabla!$A$16,Tabla!$D$16,IF(B18=Tabla!$A$17,Tabla!$D$17,IF(B18=Tabla!$A$18,Tabla!$D$18,IF(B18=Tabla!$A$19,Tabla!$D$19,IF(B18=Tabla!$A$20,Tabla!$D$20,IF(B18=Tabla!$A$21,Tabla!$D$21,IF(B18=Tabla!$A$22,Tabla!$D$22,IF(B18=Tabla!$A$23,Tabla!$D$23,IF(B18=Tabla!$A$24,Tabla!$D$24,IF(B18=Tabla!$A$25,Tabla!$D$25,IF(B18=Tabla!$A$26,Tabla!$D$26,IF(B18=Tabla!$A$27,Tabla!$D$27,IF(B18=Tabla!$A$28,Tabla!$D$28,IF(B18=Tabla!$A$29,Tabla!$D$29,IF(B18=Tabla!$A$30,Tabla!$D$30,IF(B18=Tabla!$A$31,Tabla!$D$31,IF(B18=Tabla!$A$32,Tabla!$D$32,IF(B18=Tabla!$A$33,Tabla!$D$33)))))))))))))))))))*A18 -> 0 | H18: =+J5+100 -> 19300 | J18: =(IF(B18=Tabla!$A$16,Tabla!$C$16,IF(B18=Tabla!$A$17,Tabla!$C$17,IF(B18=Tabla!$A$18,Tabla!$C$18,IF(B18=Tabla!$A$19,Tabla!$C$19,IF(B18=Tabla!$A$20,Tabla!$C$20,IF(B18=Tabla!$A$21,Tabla!$C$21,IF(B18=Tabla!$A$22,Tabla!$C$22,IF(B18=Tabla!$A$23,Tabla!$C$23,IF(B18=Tabla!$A$24,Tabla!$C$24,IF(B18=Tabla!$A$25,Tabla!$C$25,IF(B18=Tabla!$A$26,Tabla!$C$26,IF(B18=Tabla!$A$27,Tabla!$C$27,IF(B18=Tabla!$A$28,Tabla!$C$28,IF(B18=Tabla!$A$29,Tabla!$C$29,IF(B18=Tabla!$A$30,Tabla!$C$30,IF(B18=Tabla!$A$31,Tabla!$C$31,IF(B18=Tabla!$A$32,Tabla!$C$32,IF(B18=Tabla!$A$33,Tabla!$C$33,””)))))))))))))))))))*(H18/1000)*((D10+J10)/100)*E18 -> 0 | K18: =(IF(B18=Tabla!$A$16,Tabla!$C$16,IF(B18=Tabla!$A$17,Tabla!$C$17,IF(B18=Tabla!$A$18,Tabla!$C$18,IF(B18=Tabla!$A$19,Tabla!$C$19,IF(B18=Tabla!$A$20,Tabla!$C$20,IF(B18=Tabla!$A$21,Tabla!$C$21,IF(B18=Tabla!$A$22,Tabla!$C$22,IF(B18=Tabla!$A$23,Tabla!$C$23,IF(B18=Tabla!$A$24,Tabla!$C$24,IF(B18=Tabla!$A$25,Tabla!$C$25,IF(B18=Tabla!$A$26,Tabla!$C$26,IF(B18=Tabla!$A$27,Tabla!$C$27,IF(B18=Tabla!$A$28,Tabla!$C$28,IF(B18=Tabla!$A$29,Tabla!$C$29,IF(B18=Tabla!$A$30,Tabla!$C$30,IF(B18=Tabla!$A$31,Tabla!$C$31,IF(B18=Tabla!$A$32,Tabla!$C$32,IF(B18=Tabla!$A$33,Tabla!$C$33,””)))))))))))))))))))*E18*((D10+J8)/100) -> 0 | L18: =(IF(B18=Tabla!$A$16,Tabla!$C$16,IF(B18=Tabla!$A$17,Tabla!$C$17,IF(B18=Tabla!$A$18,Tabla!$C$18,IF(B18=Tabla!$A$19,Tabla!$C$19,IF(B18=Tabla!$A$20,Tabla!$C$20,IF(B18=Tabla!$A$21,Tabla!$C$21,IF(B18=Tabla!$A$22,Tabla!$C$22,IF(B18=Tabla!$A$23,Tabla!$C$23,IF(B18=Tabla!$A$24,Tabla!$C$24,IF(B18=Tabla!$A$25,Tabla!$C$25,IF(B18=Tabla!$A$26,Tabla!$C$26,IF(B18=Tabla!$A$27,Tabla!$C$27,IF(B18=Tabla!$A$28,Tabla!$C$28,IF(B18=Tabla!$A$29,Tabla!$C$29,IF(B18=Tabla!$A$30,Tabla!$C$30,IF(B18=Tabla!$A$31,Tabla!$C$31,IF(B18=Tabla!$A$32,Tabla!$C$32,IF(B18=Tabla!$A$33,Tabla!$C$33,””)))))))))))))))))))*E18*(D9/100) -> 0 | M18: U$S | N18: =((J18*F18)/(J5/1000)) -> 0 | O18: U$S | P18: =N18/(SUM(L16:L18)) -> 0 | Q18: U$S | R18: =IF(R6>1,((+N18/(100/D3))/R6),+N18/(100/D3)) -> 0 | S18: =(R18*100)/(Q12-R43-R44) -> 0 | T18: %
A19: =IF(D7="SI",1,0) -> 1 | B19: Costo Impresora | E19: Prep | F19: Prod | G19: Prep | H19: SobreImpresion | J19: Valor Hs
A20: =IF(F7="SI",1,0) -> 0 | B20: Reprint | E20: =(Tabla!$D$5*R8+1*R9)*A19 -> 1.5 | F20: =(+J5/20000)*A19 -> 0.96 | G20: =(Tabla!$D$5/3)*A20 -> 0 | H20: =(J5/20000)*A20 -> 0 | J20: U$S | K20: =+Tabla!$B$5 -> 58.46 | M20: U$S | N20: =((E20+F20+G20+H20)*K20)/(J5/1000)*A19 -> 7.4901875 | O20: U$S | P20: =N20/(SUM(L16:L18)) -> 0.10101127 | Q20: U$S | R20: =IF(R6>1,((+N20/(100/D3))/R6),+N20/(100/D3)) -> 1.797645 | S20: =(R20*100)/(Q12-R43-R44) -> 1.4038111 | T20: %
A21: =IF(D7="SI",1,0) -> 1 | B21: Tela Doble Fax | I21: =(+L21/S10)*A20 -> 0 | J21: x Color U$S | L21: =(IF(B21=Tabla!$A$79,((Tabla!$B$79/2300/46)*(D10+J8)*N9),1)*0.75) -> 9.9278592 | O21: U$S | P21: =((I21+L21*S10)/J6)*A21 -> 0.048812331 | Q21: U$S | R21: =IF(R6>1,((((I21+L21*R10)/(J4/1000)*A21))/R6),((I21+L21*R10)/(J4/1000)*A21)) -> 0.86868768 | S21: =(R21*100)/(Q12-R43-R44) -> 0.67837278 | T21: %
A22: =IF(D7="SI",1,0) -> 1 | B22: Tintas + Diluyentes | I22: =(((Tabla!$B$90*0.8)+(Tabla!$B$93*0.2))/1000*2)*A20 -> 0 | J22: Valor grs/mts2 | L22: =(((((Tabla!$J$116-Tabla!$E$116)/1000*2)+((Tabla!$E$116/1000*2)*S9)/100)*R11)/100)+I22 -> 0.030711123 | M22: U$S | N22: =(L22*((D10+J8)*10)*A22)*(R10/8) -> 17.466951 | O22: U$S | P22: =N22/(SUM(L16:L18)) -> 0.23555604 | Q22: U$S | R22: =IF(R6>1,((+N22/(100/D3))/R6),+N22/(100/D3)) -> 4.1920683 | S22: =(R22*100)/(Q12-R43-R44) -> 3.2736565 | T22: %
A23: =IF(D7="SI",1,0) -> 1 | B23: Limpieza Diluyentes | E23: =IF(J5>240000,120,IF(J5>210000,96,IF(J5>180000,72,IF(J5>150000,64,IF(J5>120000,48,IF(J5>60000,24,IF(J5>30000,16,12))))))) -> 12 | J23: Valor Lts | L23: =+Tabla!$B$99 -> 1.25 | M23: U$S | N23: =(+L23*E23/J5*1000)*A23 -> 0.78125 | O23: U$S | P23: =N23/(SUM(L16:L18)) -> 0.010535791 | Q23: U$S | R23: =IF(R6>1,((+N23/(100/D3))/R6),+N23/(100/D3)) -> 0.1875 | S23: =(R23*100)/(Q12-R43-R44) -> 0.1464219 | T23: %
A24: =IF(J7="SI",1,IF(J7="BI",2,0)) -> 1 | B24: Costo Laminado | E24: =+Tabla!$D$6*(A24+A26) -> 0.5 | F24: =+J5/Tabla!$C$6*(A25+A26) -> 1.2 | J24: U$S | K24: =+Tabla!$B$6 -> 41.35 | M24: U$S | N24: =((E24+F24)*K24)/(J5/1000) -> 3.6611979 | O24: U$S | P24: =N24/(SUM(L16:L18)) -> 0.04937423 | Q24: U$S | R24: =IF(R6>1,((+N24/(100/D3))/R6),+N24/(100/D3)) -> 0.8786875 | S24: =(R24*100)/(Q12-R43-R44) -> 0.68618181 | T24: %
A25: =IF(J7="SI",1,IF(J7="BI",2,0)) -> 1 | B25: Solvent Less | J25: Valor grs/mts2 | L25: =IF(J7="SI",+(((Tabla!$B$123/1000*Tabla!$C$123)+(Tabla!$B$124/1000*Tabla!C350))*Tabla!$B$122)*A25,IF(J7="BI",+(((Tabla!$B$123/1000*Tabla!$C$123)+(Tabla!$B$124/1000*Tabla!C350))*Tabla!$B$122)*A25,0)) -> 0.012474 | M25: U$S | N25: =L25*((D10+J9+J10)*10) -> 8.1081 | O25: U$S | P25: =N25/(SUM(L16:L18)) -> 0.10934432 | Q25: U$S | R25: =IF(R6>1,((+N25/(100/D3))/R6),+N25/(100/D3)) -> 1.945944 | S25: =(R25*100)/(Q12-R43-R44) -> 1.5196203 | T25: %
A26: =IF(N7="SI",1,IF(N7="BI",2,0)) -> 0 | B26: Solvent | J26: Valor grs/mts2 | L26: =IF(N7="SI",+((Tabla!$B$127/1000)*Tabla!$B$126)*A26,IF(N7="BI",+((Tabla!$B$127/1000)*Tabla!$B$126)*A26,0)) -> 0 | M26: U$S | N26: =L26*(D10*10) -> 0 | O26: U$S | P26: =N26/(SUM(L16:L18)) -> 0 | Q26: U$S | R26: =IF(R6>1,((+N26/(100/D3))/R6),+N26/(100/D3)) -> 0 | S26: =(R26*100)/(Q12-R43-R44) -> 0 | T26: %
B27: Refilado | E27: =+Tabla!$D$7 -> 0 | F27: =+J5/Tabla!$C$7 -> 2.4 | J27: U$S | K27: =+Tabla!$B$7 -> 39.54 | M27: U$S | N27: =((E27+F27)*K27)/(J5/1000) -> 4.9425 | O27: U$S | P27: =N27/(SUM(L16:L18)) -> 0.06665363 | Q27: U$S | R27: =IF(R6>1,((+N27/(100/D3))/R6),+N27/(100/D3)) -> 1.1862 | S27: =(R27*100)/(Q12-R43-R44) -> 0.92632348 | T27: %
A28: =+Tabla!$E$7 -> 0.05 | B28: % Material Scrap | M28: U$S | N28: =((SUM(P16:P27))*A28) -> 0.20696975 | O28: U$S | P28: =((SUM(P16:P27))*A28) -> 0.20696975 | Q28: U$S | R28: =+N28/(100/D3) -> 0.049672741 | S28: =(R28*100)/(Q12-R43-R44) -> 0.038790277 | T28: %
B29: Costo Bobina | O29: U$S | P29: =SUM(P16:P28) -> 4.3463649
A30: =IF(J3>=38,Tabla!$E$155,IF(J3>=25,Tabla!$E$150,IF(J3>=18,Tabla!$E$147,IF(J3>=15,Tabla!$E$144,Tabla!$E$139))))-(A31*Tabla!$G$139) -> 30 | B30: Costo Confeccionadora | E30: 1 | F30: =+J4/+(A30*60) -> 44.444444 | J30: U$S | K30: =+Tabla!$B$8 -> 60.01 | L30: =+(((+E30+F30)*K30)/J4)*1000 -> 34.089014 | M30: U$S | N30: =((E30+F30)*K30)/(J5/1000) -> 142.03756 | O30: U$S | P30: =N30/(SUM(L16:L18)) -> 1.9154919 | Q30: U$S | R30: =+N30/(100/D3) -> 34.089014 | S30: =(R30*100)/(Q12-R43-R44) -> 26.620683 | T30: %
A31: =IF(S3="SI",1,0) -> 0 | B31: Zipper | E31: Scrap | F31: =+Tabla!$F$8 -> 100 | M31: U$S | N31: =+Tabla!$B$132*(1000+F31)*A31 -> 0 | O31: U$S | P31: =N31/(SUM(L16:L18)) -> 0 | Q31: U$S | R31: =+N31/(100/D3) -> 0 | S31: =(R31*100)/(Q12-R43-R44) -> 0 | T31: %
A32: =IF(S4="SI",1,0) -> 0 | B32: Troquel | E32: Scrap | F32: =+Tabla!$F$8 -> 100 | M32: U$S | N32: =+Tabla!$E$132*(1000+F32)*A32 -> 0 | O32: U$S | P32: =N32/(SUM(L16:L18)) -> 0 | Q32: U$S | R32: =+Tabla!$E$132*(1000+F32)*A32 -> 0 | S32: =(R32*100)/(Q12-R43-R44) -> 0 | T32: %
A33: =+Tabla!$E$8 -> 0.15 | B33: Scrap Confeccionadora | M33: U$S | N33: =+(P29*A33)/(100000/J3)*1000 -> 0.35205555 | O33: U$S | P33: =N33/(SUM(L16:L18)) -> 0.0047477553 | Q33: U$S | R33: =SUM(R16:R31)*A33 -> 16.170802 | S33: =(R33*100)/(Q12-R43-R44) -> 12.628051 | T33: %
A34: =+Tabla!$C$10 -> 20 | B34: Costo Picotera | E34: =+Tabla!$D$10 -> 0.5 | F34: =+J4/+(A34*60) -> 66.666667 | J34: U$S | K34: =+Tabla!$B$10 -> 20.003333 | L34: =+(((+E34+F34)*K34)/J4)*1000 -> 16.794465 | M34: U$S | N34: =((E34+F34)*K34)/(J5/1000) -> 69.976939 | O34: U$S | P34: =N34/(SUM(L16:L18)) -> 0.9436959 | Q34: U$S | R34: =+N34/(100/D3)*A35 -> 0 | S34: =(R34*100)/(Q12-R43-R44) -> 0 | T34: %
A35: =IF(S5="SI",1,0) -> 0 | B35: Picos | E35: Scrap | F35: =+Tabla!$F$10 -> 100 | M35: U$S | N35: =+Tabla!$E$133*(1000+F35)*A35 -> 0 | O35: U$S | P35: =N35/(SUM(L16:L18)) -> 0 | Q35: U$S | R35: =+Tabla!$E$133*(1000+F35)*A35 -> 0 | S35: =(R35*100)/(Q12-R43-R44) -> 0 | T35: %
A36: =+Tabla!$E$10 -> 0.05 | B36: Scrap Picotera | M36: U$S | N36: =+(P29*A36)/(100000/J3)*1000 -> 0.11735185 | O36: U$S | P36: =N36/(SUM(L16:L18)) -> 0.0015825851 | Q36: U$S | R36: =SUM(R16:R35)*A36*A35 -> 0 | S36: =(R36*100)/(Q12-R43-R44) -> 0 | T36: %
A37: =IF(J3>22.1,400,IF(J3>=15,1000,IF(J3>=12,1500,2000))) -> 400 | B37: x Caja | M37: U$S | N37: =+Tabla!$B$133/A37*1000 -> 0.94110561 | O37: U$S | P37: =N37/(SUM(L16:L18)) -> 0.012691574 | Q37: U$S | R37: =1000/A37*N37 -> 2.352764 | S37: =(R37*100)/(Q12-R43-R44) -> 1.8373129 | T37: %
A38: =+T11 -> 2 | B38: Flete | D38: =+S12 -> Caba | E38: =+T12 -> 900 | F38: =INDEX(Tabla!$B$162:$E$187,MATCH(S12,Tabla!$A$162:$A$187,0),MATCH(T12,Tabla!$B$161:$E$161,0))*A38 -> 114.36436 | O38: U$S | P38: =F38/(SUM(J6)) -> 0.080327933 | Q38: U$S | R38: =+J6*P38/J4*1000 -> 1.4295545 | S38: =(R38*100)/(Q12-R43-R44) -> 1.1163631 | T38: %
A39: =IF(J11="SI",1,0) -> 0 | B39: Extras | O39: U$S | P39: =(+L11/J6)*A39 -> 0 | Q39: U$S | R39: =(+L11/J4)*A39 -> 0 | S39: =(R39*100)/(Q12-R43-R44) -> 0 | T39: %
B40: Costo Envase | O40: U$S | P40: =SUM(P30:P39) -> 2.9585377 | S40: =(SUM(R20,R24,R27,R30)+SUM(A42:A44)+E43)/100 -> 0.77951546 | T40: Costo Produc
A41: Rentabilidad | K41: Financiado | L41: Costo Bruto | O41: U$S | P41: =+P40+P29 -> 7.3049025 | Q41: U$S | R41: =SUM(R16:R39)+(R45*A45) -> 127.75847 | S41: Costo Financiación Bancaria
A42: =IF(AND(J3<=18,J6<=Tabla!$B$217),Tabla!$B$218,IF(AND(J3<=18,J6<=Tabla!$C$217),Tabla!$C$218,IF(AND(J3<=18,J6<=Tabla!$D$217),Tabla!$D$218,IF(AND(J3<=18,J6<=Tabla!$E$217),Tabla!$E$218,IF(AND(J3<=18,J6<=Tabla!$F$217),Tabla!$F$218,IF(AND(J3<=18,J6<=Tabla!$G$217),Tabla!$G$218,IF(AND(J3<=18,J6<=Tabla!$H$217),Tabla!$H$218,IF(AND(J3<=18,J6<=Tabla!$I$217),Tabla!$I$218,IF(AND(J3>=18,J6<=Tabla!$B$217),Tabla!$B$220,IF(AND(J3>=18,J6<=Tabla!$C$217),Tabla!$C$220,IF(AND(J3>=18,J6<=Tabla!$D$217),Tabla!$D$220,IF(AND(J3>=18,J6<=Tabla!$E$217),Tabla!$E$220,IF(AND(J3>=18,J6<=Tabla!$F$217),Tabla!$F$220,IF(AND(J3>=18,J6<=Tabla!$G$217),Tabla!$G$220,IF(AND(J3>=18,J6<=Tabla!$H$217),Tabla!$H$220,Tabla!$I$220))))))))))))))) -> 38 | B42: % Plus | C42: Cliente | E42: =+K1 -> A | F42: U$S | G42: =+I42*J6 -> 6473.0958 | I42: =+((((R42*J4)/1000)/J6)) -> 4.5466124 | J42: xKg | K42: =+((((T44*J4)/1000)/J6)) -> 4.0307462 | L42: Rentabilidad Bobina | O42: U$S | P42: =(P46*(A42/100)) -> 4.6264383 | Q42: U$S | R42: =(R46*(A42/100)) -> 80.913697 | S42: U$S | T42: =+R50-R48 -> 9.180604
A43: =IF(K1="A",Tabla!$J$217,IF(K1="B",Tabla!$K$217,IF(K1="C",Tabla!$L$217,Tabla!$M$217))) -> 0 | B43: % | C43: Ajuste | E43: =+N1 -> 0 | F43: U$S | G43: =+I43*J6 -> 7192.8551 | I43: =+((((T46*J4)/1000)/J6)) -> 5.0521614 | J43: xKg | K43: =K42*J6 -> 5738.6475 | L43: Confección | O43: U$S | P43: =+P48-P41-P44 -> 4.6264383 | Q43: U$S | R43: =+R48-R41-R44 -> 80.913697 | S43: Rentabilidad Bonificando
A44: =IF(S1="AK",Tabla!$B$191,IF(S1="PM",Tabla!$B$192,IF(S1="4P",Tabla!$B$193,Tabla!$B$194)))+T2 -> 2 | B44: % Comision | E44: =+S1 -> AK | F44: U$S | G44: =+I44*J6 -> 340.68925 | I44: =+(((R44*J4)/1000)/J6) -> 0.23929539 | J44: xKg | K44: Bonificación | L44: U$S | M44: =+I43-P43 -> 0.42572312 | O44: U$S | P44: =+P46*(A44/100) -> 0.24349675 | Q44: U$S | R44: =+R48*(A44/100) -> 4.2586157 | S44: U$S | T44: =+R43-T42 -> 71.733093
A45: 0 | B45: Costo Polímeros | E45: 1 | F45: U$S | G45: =+(D10*(N9+3)*S10*0.055) -> 1426.425 | I45: =+G45/J6 -> 1.0019011 | J45: xKg | K45: =+G43-K43 -> 1454.2077 | O45: U$S | P45: =+I45*A45 -> 0 | Q45: U$S | R45: =(+J6*I45/J4*1000)*A45 -> 0
B46: Rentabilidad Bonificando Polímeros | F46: U$S | G46: =+I46*J6 -> 7192.8551 | I46: =I43-(I45*E45*A45) -> 5.0521614 | J46: xKg | O46: U$S | P46: =+P41/(1-((A42+A44)/100)) -> 12.174838 | Q46: U$S | R46: =+R41/(1-((A42+A44)/100)) -> 212.93078 | S46: =+T46/R50 -> 0.4048 | T46: =+R50-R41-T47 -> 89.910689
O47: U$S | P47: =+P46*(E43/100) -> 0 | Q47: U$S | R47: =+R46*(E43/100) -> 0 | T47: =+R50*(A44/100) -> 4.4422277
F48: Valor por Millar al contado | O48: U$S | P48: =+P46+P47 -> 12.174838 | Q48: U$S | R48: =+R46+R47 -> 212.93078 | T48: =SUM(T46:T47) -> 94.352917
Q49: U$S | R49: =(+R41/(1-((A42+(A44+(A44*N13)))/100)))+R46*(E43/100) -> 213.22693
F50: Valor por Kgrs a | J50: =+K13 -> 30 | K50: días FF | M50: =+N13 -> 0.041666667 | O50: U$S | P50: =+(P48*M50)+P48 -> 12.682122 | Q50: U$S | R50: =+(R49*M50)+R49 -> 222.11139
